{
  "behavioral_states": {
    "n_states": 5,
    "states": {
      "state_0": {
        "occurrence_rate": 0.5243534824686658,
        "total_frames": 3305,
        "total_duration_sec": 110.16666666666667,
        "n_bouts": 137,
        "mean_bout_duration_sec": 0.8041362530413625,
        "median_bout_duration_sec": 0.13333333333333333,
        "max_bout_duration_sec": 11.266666666666667,
        "feature_profile": {
          "speed_kp0": {
            "mean": 22.916270290729535,
            "std": 38.01143092965617,
            "median": 11.27709804074466
          },
          "speed_kp1": {
            "mean": 46.00276434430955,
            "std": 71.28284481271476,
            "median": 13.303564981978193
          },
          "speed_kp2": {
            "mean": 30.070169391804814,
            "std": 58.064520821511806,
            "median": 10.013013405579393
          },
          "speed_kp3": {
            "mean": 14.915942356255933,
            "std": 21.934247575103054,
            "median": 7.8154313299736256
          },
          "speed_kp4": {
            "mean": 22.00483006269047,
            "std": 59.065889794829985,
            "median": 10.305982164310848
          },
          "speed_kp5": {
            "mean": 184.06008692844722,
            "std": 350.7046931900595,
            "median": 16.020713568755838
          },
          "speed_kp6": {
            "mean": 18.169722058922503,
            "std": 53.408288664035,
            "median": 5.94033772895329
          },
          "speed_kp7": {
            "mean": 28.881312808325745,
            "std": 135.86378974944176,
            "median": 5.4746235752884385
          },
          "dist_pair0": {
            "mean": 20.003800287622607,
            "std": 8.239164845342323,
            "median": 17.92826590163214
          },
          "dist_pair1": {
            "mean": 18.368943763980376,
            "std": 8.164975120609817,
            "median": 16.1099241189962
          },
          "dist_pair2": {
            "mean": 46.18410940579151,
            "std": 3.0250035280921237,
            "median": 45.8149996224862
          },
          "dist_pair3": {
            "mean": 60.96329969195379,
            "std": 7.076415054023604,
            "median": 61.1600220705953
          },
          "dist_pair4": {
            "mean": 62.55720674719004,
            "std": 16.79364015204864,
            "median": 62.71527904524509
          },
          "dist_pair5": {
            "mean": 103.81140028052559,
            "std": 4.765137702992006,
            "median": 104.38247669276414
          },
          "dist_pair6": {
            "mean": 138.95845286472712,
            "std": 6.3056390115943906,
            "median": 140.472559943664
          },
          "dist_pair7": {
            "mean": 17.211859736964147,
            "std": 9.119195669311097,
            "median": 13.029725433152647
          },
          "dist_pair8": {
            "mean": 49.18994050732297,
            "std": 5.19600494700773,
            "median": 48.79418915165745
          },
          "dist_pair9": {
            "mean": 73.75877940607921,
            "std": 8.308628331087798,
            "median": 73.85125958812523
          },
          "dist_pair10": {
            "mean": 75.9678347979407,
            "std": 15.745105328046977,
            "median": 75.84320964590961
          },
          "dist_pair11": {
            "mean": 110.45567619745592,
            "std": 6.120019734203512,
            "median": 111.27705828572881
          },
          "dist_pair12": {
            "mean": 157.4796946505086,
            "std": 9.119437545199162,
            "median": 154.82304329102973
          },
          "dist_pair13": {
            "mean": 60.039068755932966,
            "std": 7.890728082030125,
            "median": 58.25974176279193
          },
          "dist_pair14": {
            "mean": 78.17093715764813,
            "std": 8.42627151966701,
            "median": 77.32283952631457
          },
          "dist_pair15": {
            "mean": 79.34807160298492,
            "std": 17.135517019923697,
            "median": 78.75032992341461
          },
          "dist_pair16": {
            "mean": 119.68773364748523,
            "std": 6.1198247497077904,
            "median": 118.70142839322327
          },
          "dist_pair17": {
            "mean": 148.22166093494772,
            "std": 8.948638512852392,
            "median": 149.1448375609586
          },
          "dist_pair18": {
            "mean": 39.55789384116895,
            "std": 2.469979274467519,
            "median": 39.78736311441258
          },
          "dist_pair19": {
            "mean": 44.519791991489505,
            "std": 10.203134543756104,
            "median": 42.69194668193798
          },
          "dist_pair20": {
            "mean": 62.41468246234239,
            "std": 4.298708724424092,
            "median": 63.574253608628325
          },
          "dist_pair21": {
            "mean": 155.21069114316666,
            "std": 3.742756134940609,
            "median": 155.338923301753
          },
          "dist_pair22": {
            "mean": 15.784296258584552,
            "std": 21.083992057939138,
            "median": 4.710988839097531
          },
          "dist_pair23": {
            "mean": 52.08904135297228,
            "std": 6.4170050921244135,
            "median": 50.976145203865194
          },
          "dist_pair24": {
            "mean": 123.61330009970115,
            "std": 5.665476805632393,
            "median": 123.03414184788299
          },
          "dist_pair25": {
            "mean": 54.59549213129785,
            "std": 17.889823982698633,
            "median": 53.05576489927891
          },
          "dist_pair26": {
            "mean": 124.38055551259968,
            "std": 19.72437088924142,
            "median": 120.35139912340698
          },
          "dist_pair27": {
            "mean": 162.42800045920896,
            "std": 9.690338146546342,
            "median": 161.8804504281229
          },
          "centroid_speed": {
            "mean": 32.85747672406645,
            "std": 46.345067788514065,
            "median": 11.98929128308115
          },
          "body_orientation": {
            "mean": -1.6682580355049719,
            "std": 0.3748109967288357,
            "median": -1.7885301165118384
          },
          "elongation": {
            "mean": 1.304459084621076,
            "std": 0.13544672408217023,
            "median": 1.2800078793444716
          },
          "angular_velocity": {
            "mean": -0.5715038865514672,
            "std": 6.132843599495855,
            "median": -0.013198077118006246
          },
          "movement_entropy": {
            "mean": 0.26006058585706765,
            "std": 0.41025328148168366,
            "median": 0.07719693495147985
          },
          "speed_mean_window": {
            "mean": 53.00978216051569,
            "std": 42.74601483685457,
            "median": 42.00092083522053
          },
          "speed_std_window": {
            "mean": 139.86088404383995,
            "std": 117.18796149202531,
            "median": 119.26025654417886
          },
          "speed_max_window": {
            "mean": 1006.8365614316896,
            "std": 832.6476442523167,
            "median": 963.2796047469026
          },
          "speed_p90_window": {
            "mean": 100.78030337046438,
            "std": 107.72695625311601,
            "median": 56.63805294516973
          },
          "dist_mean_window": {
            "mean": 81.06148313255815,
            "std": 3.0622375252630496,
            "median": 80.4118759149735
          },
          "dist_std_window": {
            "mean": 46.55070161223318,
            "std": 1.887125455022178,
            "median": 46.30277061496714
          },
          "angular_vel_mean_window": {
            "mean": 2.101519259488099,
            "std": 2.9663290087887266,
            "median": 1.1243923428444234
          },
          "angular_vel_max_window": {
            "mean": 13.786168255813154,
            "std": 21.824977562093448,
            "median": 5.298209759581547
          }
        }
      },
      "state_1": {
        "occurrence_rate": 0.15928922735205459,
        "total_frames": 1004,
        "total_duration_sec": 33.46666666666667,
        "n_bouts": 105,
        "mean_bout_duration_sec": 0.3187301587301587,
        "median_bout_duration_sec": 0.1,
        "max_bout_duration_sec": 5.233333333333333,
        "feature_profile": {
          "speed_kp0": {
            "mean": 27.92245043138013,
            "std": 46.458209131785374,
            "median": 13.476131352303934
          },
          "speed_kp1": {
            "mean": 50.74197082437205,
            "std": 73.71072767769056,
            "median": 15.691202195713334
          },
          "speed_kp2": {
            "mean": 35.75093473223412,
            "std": 52.382991994531864,
            "median": 14.014694031127544
          },
          "speed_kp3": {
            "mean": 16.568756701762492,
            "std": 27.78673404600916,
            "median": 7.041068726589165
          },
          "speed_kp4": {
            "mean": 26.413247577224908,
            "std": 64.62831584250442,
            "median": 12.082124968782995
          },
          "speed_kp5": {
            "mean": 274.20094949417256,
            "std": 496.3304407005748,
            "median": 7.387480668023281
          },
          "speed_kp6": {
            "mean": 68.87369050698595,
            "std": 176.8431930705808,
            "median": 6.612980687411216
          },
          "speed_kp7": {
            "mean": 17.376141623204568,
            "std": 107.1322484849633,
            "median": 4.554021568732054
          },
          "dist_pair0": {
            "mean": 23.892320064657746,
            "std": 9.540108082711729,
            "median": 24.30185151277388
          },
          "dist_pair1": {
            "mean": 24.89233094436832,
            "std": 9.41051852886013,
            "median": 26.2637219509458
          },
          "dist_pair2": {
            "mean": 45.025448572524844,
            "std": 3.533418170583589,
            "median": 45.2804039762092
          },
          "dist_pair3": {
            "mean": 55.77562281935274,
            "std": 8.001690771842277,
            "median": 56.35692405462585
          },
          "dist_pair4": {
            "mean": 124.16869812485182,
            "std": 17.2320740665671,
            "median": 119.0054351182024
          },
          "dist_pair5": {
            "mean": 94.45202289271727,
            "std": 12.460145528348457,
            "median": 97.98544613702421
          },
          "dist_pair6": {
            "mean": 128.3083989284948,
            "std": 10.864167231404934,
            "median": 128.52872714587195
          },
          "dist_pair7": {
            "mean": 23.805891708612723,
            "std": 10.998588772609232,
            "median": 25.246483953533794
          },
          "dist_pair8": {
            "mean": 47.4910015387317,
            "std": 5.2987351676549945,
            "median": 47.3638667574655
          },
          "dist_pair9": {
            "mean": 70.82721766339762,
            "std": 9.67205569112878,
            "median": 72.35029451122382
          },
          "dist_pair10": {
            "mean": 144.7416269764806,
            "std": 17.394499786319347,
            "median": 149.3775338211505
          },
          "dist_pair11": {
            "mean": 101.53809999783509,
            "std": 12.927534659786565,
            "median": 102.30175107454502
          },
          "dist_pair12": {
            "mean": 148.75780883400654,
            "std": 12.561835262832894,
            "median": 151.0234917847602
          },
          "dist_pair13": {
            "mean": 64.26971827716706,
            "std": 8.051339136007496,
            "median": 62.89285349673832
          },
          "dist_pair14": {
            "mean": 79.4619313221072,
            "std": 9.987203310484784,
            "median": 78.90565931955436
          },
          "dist_pair15": {
            "mean": 130.12300083405165,
            "std": 21.341001625355933,
            "median": 125.43823106772554
          },
          "dist_pair16": {
            "mean": 116.4379472946159,
            "std": 9.917491869959287,
            "median": 117.17371943717441
          },
          "dist_pair17": {
            "mean": 133.66522071963277,
            "std": 18.74774936161227,
            "median": 136.27424115586598
          },
          "dist_pair18": {
            "mean": 37.78103133037759,
            "std": 2.802384401283893,
            "median": 37.63645237966557
          },
          "dist_pair19": {
            "mean": 149.53794491067814,
            "std": 16.27764265931424,
            "median": 154.30266202449099
          },
          "dist_pair20": {
            "mean": 55.94488395024845,
            "std": 7.129592776844738,
            "median": 56.05064854231102
          },
          "dist_pair21": {
            "mean": 154.62130105290254,
            "std": 4.573454785494502,
            "median": 154.49120208923313
          },
          "dist_pair22": {
            "mean": 125.2424438092628,
            "std": 18.29062666536423,
            "median": 131.40801972822123
          },
          "dist_pair23": {
            "mean": 47.82977834295908,
            "std": 12.839476356387754,
            "median": 49.59826706396673
          },
          "dist_pair24": {
            "mean": 130.44167514222684,
            "std": 8.954768524894455,
            "median": 126.91787208588869
          },
          "dist_pair25": {
            "mean": 163.70960426703792,
            "std": 21.988046349117635,
            "median": 166.1563893118688
          },
          "dist_pair26": {
            "mean": 10.388384130320414,
            "std": 20.67854093427518,
            "median": 1.8223025872846355
          },
          "dist_pair27": {
            "mean": 169.2148295992082,
            "std": 14.893948503996754,
            "median": 167.18316342540913
          },
          "centroid_speed": {
            "mean": 49.77076171024079,
            "std": 64.82153613838707,
            "median": 19.024627405253355
          },
          "body_orientation": {
            "mean": -1.4836298934678749,
            "std": 0.3801286462087216,
            "median": -1.6036284757085226
          },
          "elongation": {
            "mean": 1.9159127409325218,
            "std": 0.3822168979989384,
            "median": 1.8096554491278618
          },
          "angular_velocity": {
            "mean": -0.0620124297749353,
            "std": 2.937011677452342,
            "median": 0.00039405009064741314
          },
          "movement_entropy": {
            "mean": 0.1386214385798351,
            "std": 0.20634831293126557,
            "median": 0.05176810214970981
          },
          "speed_mean_window": {
            "mean": 65.15155831169163,
            "std": 45.12021914735307,
            "median": 56.124057558658166
          },
          "speed_std_window": {
            "mean": 187.1632673683349,
            "std": 118.825330992576,
            "median": 184.86124003229233
          },
          "speed_max_window": {
            "mean": 1381.8177533853172,
            "std": 810.8527181589342,
            "median": 1614.0214778123727
          },
          "speed_p90_window": {
            "mean": 123.12633140176166,
            "std": 132.04162099741458,
            "median": 76.56967420656784
          },
          "dist_mean_window": {
            "mean": 90.3867974419309,
            "std": 4.201898175421243,
            "median": 92.23281204384274
          },
          "dist_std_window": {
            "mean": 49.56924689313785,
            "std": 2.5816492993732525,
            "median": 50.45892512672389
          },
          "angular_vel_mean_window": {
            "mean": 1.0914678219742404,
            "std": 1.8183114277134447,
            "median": 0.709783689960109
          },
          "angular_vel_max_window": {
            "mean": 5.529643572117958,
            "std": 12.516894525348789,
            "median": 2.947726042439245
          }
        }
      },
      "state_2": {
        "occurrence_rate": 0.09281294621608757,
        "total_frames": 585,
        "total_duration_sec": 19.5,
        "n_bouts": 26,
        "mean_bout_duration_sec": 0.75,
        "median_bout_duration_sec": 0.2,
        "max_bout_duration_sec": 11.2,
        "feature_profile": {
          "speed_kp0": {
            "mean": 48.54864886924786,
            "std": 65.83247455364753,
            "median": 28.03266314819588
          },
          "speed_kp1": {
            "mean": 46.31636584050381,
            "std": 39.76299194784303,
            "median": 36.0118313933926
          },
          "speed_kp2": {
            "mean": 91.0465106762527,
            "std": 137.7968275271394,
            "median": 40.878946277811316
          },
          "speed_kp3": {
            "mean": 25.261352061948816,
            "std": 25.405066181735716,
            "median": 17.140595956939897
          },
          "speed_kp4": {
            "mean": 32.17524754335954,
            "std": 70.00910510794188,
            "median": 16.475619234636987
          },
          "speed_kp5": {
            "mean": 295.88830772054564,
            "std": 495.862178295894,
            "median": 7.614644500645125
          },
          "speed_kp6": {
            "mean": 27.12172938540244,
            "std": 44.54619115352314,
            "median": 13.650878937335548
          },
          "speed_kp7": {
            "mean": 23.5870059187259,
            "std": 83.51998656321169,
            "median": 6.8250195487491485
          },
          "dist_pair0": {
            "mean": 13.501395137628837,
            "std": 5.0403746008923145,
            "median": 12.501463817949443
          },
          "dist_pair1": {
            "mean": 25.299121813420243,
            "std": 9.309991188594221,
            "median": 27.69466865628749
          },
          "dist_pair2": {
            "mean": 43.59126915795261,
            "std": 3.8624099133114838,
            "median": 43.42496067902267
          },
          "dist_pair3": {
            "mean": 64.4463568286701,
            "std": 7.45854017312793,
            "median": 65.82853490601364
          },
          "dist_pair4": {
            "mean": 171.2056256323467,
            "std": 25.562555502692412,
            "median": 180.97644667746854
          },
          "dist_pair5": {
            "mean": 91.44894093948199,
            "std": 6.292267937741779,
            "median": 92.54015597135981
          },
          "dist_pair6": {
            "mean": 182.4817565916892,
            "std": 7.13973505129892,
            "median": 183.88442407923952
          },
          "dist_pair7": {
            "mean": 17.38766873668806,
            "std": 7.928435487636643,
            "median": 17.183376621475475
          },
          "dist_pair8": {
            "mean": 41.10008896782549,
            "std": 3.429361864954687,
            "median": 40.64525085291294
          },
          "dist_pair9": {
            "mean": 69.16040603205379,
            "std": 7.311939826406856,
            "median": 69.80833537749575
          },
          "dist_pair10": {
            "mean": 178.11678422687956,
            "std": 25.551600001470607,
            "median": 187.4623023500465
          },
          "dist_pair11": {
            "mean": 90.5128345084133,
            "std": 5.90200514672864,
            "median": 91.12775484147119
          },
          "dist_pair12": {
            "mean": 189.60034863115823,
            "std": 7.279960508794959,
            "median": 191.91664354834208
          },
          "dist_pair13": {
            "mean": 55.84968706276139,
            "std": 7.526607318320107,
            "median": 55.09017586825103
          },
          "dist_pair14": {
            "mean": 84.89550061543343,
            "std": 9.802782268713237,
            "median": 85.21161128077989
          },
          "dist_pair15": {
            "mean": 193.3994289990121,
            "std": 27.066709230425996,
            "median": 200.5313477300667
          },
          "dist_pair16": {
            "mean": 105.07086422971133,
            "std": 8.113670933863622,
            "median": 105.33723336130886
          },
          "dist_pair17": {
            "mean": 204.90805308301827,
            "std": 10.3682713485607,
            "median": 204.88618758784395
          },
          "dist_pair18": {
            "mean": 38.62649788069625,
            "std": 2.81457072491281,
            "median": 39.32888864525232
          },
          "dist_pair19": {
            "mean": 147.11399243719666,
            "std": 25.146843898472543,
            "median": 154.96072524902013
          },
          "dist_pair20": {
            "mean": 49.860421498607955,
            "std": 3.5618276836775,
            "median": 50.807124323677236
          },
          "dist_pair21": {
            "mean": 158.6821118595187,
            "std": 5.695320621633038,
            "median": 161.2201650959342
          },
          "dist_pair22": {
            "mean": 110.53820804744709,
            "std": 24.543042878365156,
            "median": 120.25766799244938
          },
          "dist_pair23": {
            "mean": 42.53379400600945,
            "std": 5.142958542585529,
            "median": 41.701423185531446
          },
          "dist_pair24": {
            "mean": 121.89387993765851,
            "std": 5.937197606666336,
            "median": 123.219026976948
          },
          "dist_pair25": {
            "mean": 116.05711022609252,
            "std": 23.11429316219066,
            "median": 123.92167463397749
          },
          "dist_pair26": {
            "mean": 14.72418141125729,
            "std": 25.289934272664336,
            "median": 1.8503916297387422
          },
          "dist_pair27": {
            "mean": 126.639735914108,
            "std": 5.945347925250299,
            "median": 125.89520544665298
          },
          "centroid_speed": {
            "mean": 52.82124950786756,
            "std": 61.488377707560325,
            "median": 23.93310601118358
          },
          "body_orientation": {
            "mean": 0.4614495315925402,
            "std": 0.050175234388916946,
            "median": 0.472486629851443
          },
          "elongation": {
            "mean": 3.948141202433733,
            "std": 0.5095238300440412,
            "median": 3.9751235838118775
          },
          "angular_velocity": {
            "mean": 0.03797455303514075,
            "std": 0.8030161727585805,
            "median": 0.003702723563129285
          },
          "movement_entropy": {
            "mean": 0.1251021996311278,
            "std": 0.1271051822322995,
            "median": 0.06328532861590816
          },
          "speed_mean_window": {
            "mean": 81.35581798164677,
            "std": 57.86429055153206,
            "median": 71.85205144647065
          },
          "speed_std_window": {
            "mean": 188.03460216735812,
            "std": 136.1292032453383,
            "median": 186.91827413421913
          },
          "speed_max_window": {
            "mean": 1290.9054665480621,
            "std": 939.1314449016006,
            "median": 1176.895749659917
          },
          "speed_p90_window": {
            "mean": 171.28847811926502,
            "std": 143.59145271025648,
            "median": 126.131912913253
          },
          "dist_mean_window": {
            "mean": 96.46756338010645,
            "std": 4.571520851859864,
            "median": 97.48456380865284
          },
          "dist_std_window": {
            "mean": 60.930565037150444,
            "std": 3.069210244420961,
            "median": 61.14194428007741
          },
          "angular_vel_mean_window": {
            "mean": 0.9166140081566404,
            "std": 1.8344698685910557,
            "median": 0.42508615555709783
          },
          "angular_vel_max_window": {
            "mean": 7.193093628711476,
            "std": 18.969737290651974,
            "median": 1.9703063898552498
          }
        }
      },
      "state_3": {
        "occurrence_rate": 0.14136125654450263,
        "total_frames": 891,
        "total_duration_sec": 29.7,
        "n_bouts": 99,
        "mean_bout_duration_sec": 0.3,
        "median_bout_duration_sec": 0.1,
        "max_bout_duration_sec": 4.5,
        "feature_profile": {
          "speed_kp0": {
            "mean": 67.52212766801806,
            "std": 143.91709132894889,
            "median": 27.39693637877989
          },
          "speed_kp1": {
            "mean": 85.14817521808108,
            "std": 154.88878336059003,
            "median": 34.74601066775926
          },
          "speed_kp2": {
            "mean": 142.20912695626708,
            "std": 442.77462612256335,
            "median": 39.99567450329153
          },
          "speed_kp3": {
            "mean": 54.578816459762955,
            "std": 147.3984523255553,
            "median": 16.419966543817953
          },
          "speed_kp4": {
            "mean": 56.735576753402384,
            "std": 158.52409838498426,
            "median": 17.294884153693154
          },
          "speed_kp5": {
            "mean": 252.62837049896896,
            "std": 407.3416079181855,
            "median": 28.48406214202532
          },
          "speed_kp6": {
            "mean": 89.35410118118386,
            "std": 224.58300125966196,
            "median": 16.99505764913837
          },
          "speed_kp7": {
            "mean": 683.147318125939,
            "std": 950.4765905520189,
            "median": 36.51700735762957
          },
          "dist_pair0": {
            "mean": 20.433239073137095,
            "std": 9.43768596450286,
            "median": 17.996302852592596
          },
          "dist_pair1": {
            "mean": 25.21267534924958,
            "std": 25.906544097026597,
            "median": 20.010831804740715
          },
          "dist_pair2": {
            "mean": 46.422589021627545,
            "std": 5.2157666538101,
            "median": 45.47598937424248
          },
          "dist_pair3": {
            "mean": 63.22139308947356,
            "std": 9.98171773089072,
            "median": 62.09766625740768
          },
          "dist_pair4": {
            "mean": 65.11898632244272,
            "std": 17.00862710250603,
            "median": 61.613743955197094
          },
          "dist_pair5": {
            "mean": 104.68771092833866,
            "std": 10.659087719914135,
            "median": 104.39516496500586
          },
          "dist_pair6": {
            "mean": 171.1730409442395,
            "std": 34.54894332883368,
            "median": 170.186200792652
          },
          "dist_pair7": {
            "mean": 22.771661842643546,
            "std": 27.13252395509347,
            "median": 16.60557018427285
          },
          "dist_pair8": {
            "mean": 48.93140554137876,
            "std": 6.105414280575016,
            "median": 48.08266506076024
          },
          "dist_pair9": {
            "mean": 75.29552724252758,
            "std": 9.033780502227069,
            "median": 74.93413019186407
          },
          "dist_pair10": {
            "mean": 77.04457216646833,
            "std": 17.834169351945615,
            "median": 75.61267929331942
          },
          "dist_pair11": {
            "mean": 111.20383563805007,
            "std": 13.404153173811382,
            "median": 111.51435045177173
          },
          "dist_pair12": {
            "mean": 184.84928674171422,
            "std": 31.918467153183958,
            "median": 182.87993240944166
          },
          "dist_pair13": {
            "mean": 64.19225602102416,
            "std": 20.778446955328427,
            "median": 60.09963465765702
          },
          "dist_pair14": {
            "mean": 84.64645211621523,
            "std": 19.47501881665555,
            "median": 79.75087038426737
          },
          "dist_pair15": {
            "mean": 85.46253318786749,
            "std": 23.023924318205218,
            "median": 81.1656434446777
          },
          "dist_pair16": {
            "mean": 123.84293345529414,
            "std": 20.822699813733305,
            "median": 120.25174265399775
          },
          "dist_pair17": {
            "mean": 189.397619363353,
            "std": 37.61809079825652,
            "median": 190.59036629481542
          },
          "dist_pair18": {
            "mean": 39.89964079525796,
            "std": 3.9304279883901176,
            "median": 39.485526712673995
          },
          "dist_pair19": {
            "mean": 44.85743061957623,
            "std": 15.88699362392446,
            "median": 42.10301090067081
          },
          "dist_pair20": {
            "mean": 63.44743042664415,
            "std": 11.067878932818042,
            "median": 63.45211189953116
          },
          "dist_pair21": {
            "mean": 151.26954041685622,
            "std": 26.334394947258552,
            "median": 149.44849762172487
          },
          "dist_pair22": {
            "mean": 16.34615496836393,
            "std": 21.07936338888134,
            "median": 5.252450063333829
          },
          "dist_pair23": {
            "mean": 50.670171786005675,
            "std": 11.193764723087382,
            "median": 50.70022174821004
          },
          "dist_pair24": {
            "mean": 120.31340943317066,
            "std": 30.04527633855045,
            "median": 117.49701564089094
          },
          "dist_pair25": {
            "mean": 56.124121502734525,
            "std": 21.667987561860322,
            "median": 53.422338498393266
          },
          "dist_pair26": {
            "mean": 121.84147081663251,
            "std": 38.90386794843131,
            "median": 117.94876268359143
          },
          "dist_pair27": {
            "mean": 113.27328534627522,
            "std": 32.864148322295414,
            "median": 110.3945149248149
          },
          "centroid_speed": {
            "mean": 141.24354858974996,
            "std": 155.38357541036643,
            "median": 100.95250092727021
          },
          "body_orientation": {
            "mean": -0.08123892398864815,
            "std": 0.7014143251732139,
            "median": 0.07963005079091762
          },
          "elongation": {
            "mean": 3.2553099318190744,
            "std": 1.60749865106389,
            "median": 2.9430021269470505
          },
          "angular_velocity": {
            "mean": 2.208268748871697,
            "std": 21.956467698676818,
            "median": 0.009881702037466411
          },
          "movement_entropy": {
            "mean": 0.03859180926473826,
            "std": 0.013135160088926779,
            "median": 0.03407808205425472
          },
          "speed_mean_window": {
            "mean": 164.44543847070955,
            "std": 130.24706078138917,
            "median": 131.64682241181822
          },
          "speed_std_window": {
            "mean": 382.2368967595449,
            "std": 155.68174812765025,
            "median": 351.3719358646206
          },
          "speed_max_window": {
            "mean": 2554.5364054263914,
            "std": 925.4161246431737,
            "median": 2676.7620891349175
          },
          "speed_p90_window": {
            "mean": 309.2601601499405,
            "std": 281.9017947696711,
            "median": 239.96450691706826
          },
          "dist_mean_window": {
            "mean": 84.3578342413203,
            "std": 4.637423124986382,
            "median": 83.99520188123407
          },
          "dist_std_window": {
            "mean": 51.8199066750749,
            "std": 6.383635896069135,
            "median": 50.79466333477132
          },
          "angular_vel_mean_window": {
            "mean": 7.833700496780482,
            "std": 7.1983624714739,
            "median": 5.4268132257916095
          },
          "angular_vel_max_window": {
            "mean": 49.526502984724004,
            "std": 30.023289695617922,
            "median": 64.85383665194512
          }
        }
      },
      "state_4": {
        "occurrence_rate": 0.08218308741868952,
        "total_frames": 518,
        "total_duration_sec": 17.266666666666666,
        "n_bouts": 62,
        "mean_bout_duration_sec": 0.278494623655914,
        "median_bout_duration_sec": 0.06666666666666667,
        "max_bout_duration_sec": 2.1666666666666665,
        "feature_profile": {
          "speed_kp0": {
            "mean": 98.69765057876316,
            "std": 197.2948649575953,
            "median": 49.47469014185618
          },
          "speed_kp1": {
            "mean": 111.69301086646917,
            "std": 194.3785824581804,
            "median": 56.17799100762255
          },
          "speed_kp2": {
            "mean": 160.9994407117917,
            "std": 380.84188672044013,
            "median": 76.4352721812661
          },
          "speed_kp3": {
            "mean": 80.52283898581983,
            "std": 153.71948468388388,
            "median": 38.42890374042476
          },
          "speed_kp4": {
            "mean": 62.78341435480804,
            "std": 183.40580686335687,
            "median": 19.3830376887421
          },
          "speed_kp5": {
            "mean": 549.5600232825959,
            "std": 690.3324130680935,
            "median": 182.96746594327067
          },
          "speed_kp6": {
            "mean": 108.4869945354912,
            "std": 227.8258128880637,
            "median": 16.250212218510075
          },
          "speed_kp7": {
            "mean": 136.17839880789793,
            "std": 498.82737814153495,
            "median": 8.789371408587982
          },
          "dist_pair0": {
            "mean": 28.792211050002727,
            "std": 8.72816084131,
            "median": 31.075607425052695
          },
          "dist_pair1": {
            "mean": 41.28863543617156,
            "std": 13.33710985855183,
            "median": 40.5635190077797
          },
          "dist_pair2": {
            "mean": 40.212895132345416,
            "std": 5.179245301033782,
            "median": 40.06020177685126
          },
          "dist_pair3": {
            "mean": 55.81855761998569,
            "std": 10.109830369230542,
            "median": 53.79016510834687
          },
          "dist_pair4": {
            "mean": 66.56598481988684,
            "std": 27.575489287545146,
            "median": 63.08751576717988
          },
          "dist_pair5": {
            "mean": 96.10124793892855,
            "std": 10.890499958667009,
            "median": 96.67110732753335
          },
          "dist_pair6": {
            "mean": 102.9957486227677,
            "std": 19.60870162898627,
            "median": 101.79837202507838
          },
          "dist_pair7": {
            "mean": 41.31385397096343,
            "std": 13.670503983598953,
            "median": 41.9160670376569
          },
          "dist_pair8": {
            "mean": 44.40533012970521,
            "std": 4.595487037824914,
            "median": 44.52852305144639
          },
          "dist_pair9": {
            "mean": 75.85886814604243,
            "std": 12.777737160295757,
            "median": 77.19098419035606
          },
          "dist_pair10": {
            "mean": 78.90752914023213,
            "std": 29.5155345141997,
            "median": 81.38824933570791
          },
          "dist_pair11": {
            "mean": 111.56178661969055,
            "std": 15.518303355224441,
            "median": 115.59653618228967
          },
          "dist_pair12": {
            "mean": 115.47067224223211,
            "std": 25.582401288429686,
            "median": 117.12011987967817
          },
          "dist_pair13": {
            "mean": 75.99329913262035,
            "std": 12.514962332944513,
            "median": 76.87600295062663
          },
          "dist_pair14": {
            "mean": 94.20526299671474,
            "std": 14.200536722044992,
            "median": 92.17781024395133
          },
          "dist_pair15": {
            "mean": 72.70706795324782,
            "std": 25.85830680129881,
            "median": 71.58138247560437
          },
          "dist_pair16": {
            "mean": 133.56824732748788,
            "std": 15.337935155895039,
            "median": 132.35253653906835
          },
          "dist_pair17": {
            "mean": 91.87741241469493,
            "std": 32.379891437964446,
            "median": 81.6680838262225
          },
          "dist_pair18": {
            "mean": 42.58611652999547,
            "std": 8.07469820731666,
            "median": 40.77616791021983
          },
          "dist_pair19": {
            "mean": 83.23180948942607,
            "std": 40.6710556326739,
            "median": 75.86709440726696
          },
          "dist_pair20": {
            "mean": 69.85148708451423,
            "std": 13.663941910300625,
            "median": 72.0735355246781
          },
          "dist_pair21": {
            "mean": 134.99740991714987,
            "std": 21.78306810449522,
            "median": 137.19397694862022
          },
          "dist_pair22": {
            "mean": 78.42108981657677,
            "std": 49.3938931720313,
            "median": 80.28947690432943
          },
          "dist_pair23": {
            "mean": 45.0065069556481,
            "std": 8.71636102900572,
            "median": 44.981890543145354
          },
          "dist_pair24": {
            "mean": 129.55353249383262,
            "std": 19.241795185733807,
            "median": 131.56286694049766
          },
          "dist_pair25": {
            "mean": 115.34572979876624,
            "std": 51.74195652755037,
            "median": 118.542197475974
          },
          "dist_pair26": {
            "mean": 68.2312641870917,
            "std": 56.09135666067874,
            "median": 73.02049089139001
          },
          "dist_pair27": {
            "mean": 169.04204010179137,
            "std": 25.075495261614815,
            "median": 171.32102868393747
          },
          "centroid_speed": {
            "mean": 116.44169773551079,
            "std": 154.71549088479517,
            "median": 64.48451381907685
          },
          "body_orientation": {
            "mean": -1.1609779530289195,
            "std": 0.29688832796394027,
            "median": -1.1233557322955066
          },
          "elongation": {
            "mean": 2.1280882677505892,
            "std": 0.9479988136597977,
            "median": 1.8053059121833033
          },
          "angular_velocity": {
            "mean": 0.03182694597019945,
            "std": 5.608309446828806,
            "median": 0.04045077660017771
          },
          "movement_entropy": {
            "mean": 0.06593415788967354,
            "std": 0.1056581318741526,
            "median": 0.04466213873471195
          },
          "speed_mean_window": {
            "mean": 137.61706512061266,
            "std": 114.2049768317108,
            "median": 122.10122469371731
          },
          "speed_std_window": {
            "mean": 282.4420943818151,
            "std": 130.0186337218585,
            "median": 281.394045967033
          },
          "speed_max_window": {
            "mean": 1974.2433599111232,
            "std": 887.3949230675784,
            "median": 1889.465993108633
          },
          "speed_p90_window": {
            "mean": 304.60463454909086,
            "std": 281.6359518838435,
            "median": 250.61486967057658
          },
          "dist_mean_window": {
            "mean": 83.90176426460663,
            "std": 3.7045286378507316,
            "median": 83.75655248806551
          },
          "dist_std_window": {
            "mean": 44.1896972161939,
            "std": 2.8007276141968087,
            "median": 43.842629638624764
          },
          "angular_vel_mean_window": {
            "mean": 1.9816219031620024,
            "std": 1.9791777970995714,
            "median": 1.526501523080205
          },
          "angular_vel_max_window": {
            "mean": 10.052405060629951,
            "std": 14.515470765486034,
            "median": 5.901055637949857
          }
        }
      }
    }
  },
  "transitions": {
    "transition_matrix": [
      [
        0.9585476550680787,
        0.02118003025718608,
        0.0,
        0.015128593040847202,
        0.005143721633888048
      ],
      [
        0.06573705179282868,
        0.8954183266932271,
        0.00099601593625498,
        0.008964143426294821,
        0.02888446215139442
      ],
      [
        0.0,
        0.0,
        0.9571917808219178,
        0.04280821917808219,
        0.0
      ],
      [
        0.05948372615039282,
        0.006734006734006734,
        0.028058361391694726,
        0.8888888888888888,
        0.016835016835016835
      ],
      [
        0.03474903474903475,
        0.055984555984555984,
        0.0,
        0.02895752895752896,
        0.8803088803088803
      ]
    ],
    "transition_counts": [
      [
        3168.0,
        70.0,
        0.0,
        50.0,
        17.0
      ],
      [
        66.0,
        899.0,
        1.0,
        9.0,
        29.0
      ],
      [
        0.0,
        0.0,
        559.0,
        25.0,
        0.0
      ],
      [
        53.0,
        6.0,
        25.0,
        792.0,
        15.0
      ],
      [
        18.0,
        29.0,
        0.0,
        15.0,
        456.0
      ]
    ],
    "state_labels": [
      0,
      1,
      2,
      3,
      4
    ],
    "top_transitions": [
      {
        "from_state": 0,
        "to_state": 1,
        "count": 70,
        "probability": 0.02118003025718608
      },
      {
        "from_state": 1,
        "to_state": 0,
        "count": 66,
        "probability": 0.06573705179282868
      },
      {
        "from_state": 3,
        "to_state": 0,
        "count": 53,
        "probability": 0.05948372615039282
      },
      {
        "from_state": 0,
        "to_state": 3,
        "count": 50,
        "probability": 0.015128593040847202
      },
      {
        "from_state": 1,
        "to_state": 4,
        "count": 29,
        "probability": 0.02888446215139442
      },
      {
        "from_state": 4,
        "to_state": 1,
        "count": 29,
        "probability": 0.055984555984555984
      },
      {
        "from_state": 2,
        "to_state": 3,
        "count": 25,
        "probability": 0.04280821917808219
      },
      {
        "from_state": 3,
        "to_state": 2,
        "count": 25,
        "probability": 0.028058361391694726
      },
      {
        "from_state": 4,
        "to_state": 0,
        "count": 18,
        "probability": 0.03474903474903475
      },
      {
        "from_state": 0,
        "to_state": 4,
        "count": 17,
        "probability": 0.005143721633888048
      }
    ]
  }
}