{
  "behavioral_states": {
    "n_states": 5,
    "states": {
      "state_0": {
        "occurrence_rate": 0.0866258579113337,
        "total_frames": 467,
        "total_duration_sec": 15.566666666666666,
        "n_bouts": 37,
        "mean_bout_duration_sec": 0.4207207207207207,
        "median_bout_duration_sec": 0.03333333333333333,
        "max_bout_duration_sec": 11.8,
        "feature_profile": {
          "speed_kp0": {
            "mean": 482.197589752997,
            "std": 512.2342910473044,
            "median": 305.7790213295254
          },
          "speed_kp1": {
            "mean": 204.46917322852858,
            "std": 307.223232377466,
            "median": 120.65903558341545
          },
          "speed_kp2": {
            "mean": 658.1138699189278,
            "std": 558.6814627892918,
            "median": 561.2576426891869
          },
          "speed_kp3": {
            "mean": 303.87664889081935,
            "std": 489.6166068573796,
            "median": 66.88332281590142
          },
          "speed_kp4": {
            "mean": 67.90315216023282,
            "std": 195.10140014870578,
            "median": 5.9395045270476645
          },
          "speed_kp5": {
            "mean": 439.91899694624584,
            "std": 510.64955172302496,
            "median": 148.36155115168452
          },
          "speed_kp6": {
            "mean": 161.97552938634917,
            "std": 159.10181912011845,
            "median": 124.37716035506362
          },
          "speed_kp7": {
            "mean": 42.18147982702628,
            "std": 141.6521550024517,
            "median": 15.779057414635822
          },
          "dist_pair0": {
            "mean": 42.7006104348994,
            "std": 39.88231909699385,
            "median": 23.801833101287734
          },
          "dist_pair1": {
            "mean": 51.42484656724077,
            "std": 40.80441103840994,
            "median": 43.56146746387611
          },
          "dist_pair2": {
            "mean": 137.90966808174377,
            "std": 60.98959021772521,
            "median": 156.7265983140704
          },
          "dist_pair3": {
            "mean": 169.0633254307329,
            "std": 48.05621408932035,
            "median": 179.5659456484829
          },
          "dist_pair4": {
            "mean": 131.4261179465101,
            "std": 65.77290485425078,
            "median": 125.49388601713093
          },
          "dist_pair5": {
            "mean": 99.57514746573813,
            "std": 42.86987079893705,
            "median": 111.41660386338408
          },
          "dist_pair6": {
            "mean": 72.94533167265645,
            "std": 17.6400985047564,
            "median": 73.74482115406005
          },
          "dist_pair7": {
            "mean": 68.70722374208663,
            "std": 47.050642977016565,
            "median": 62.34090073357841
          },
          "dist_pair8": {
            "mean": 156.64259641160675,
            "std": 54.252949310835206,
            "median": 183.5148386411434
          },
          "dist_pair9": {
            "mean": 187.6205664922208,
            "std": 31.836650989512055,
            "median": 194.40913398990764
          },
          "dist_pair10": {
            "mean": 112.10712566809393,
            "std": 50.28136282107401,
            "median": 93.41037656985182
          },
          "dist_pair11": {
            "mean": 120.13857477838509,
            "std": 22.970851281569264,
            "median": 118.33712855571616
          },
          "dist_pair12": {
            "mean": 69.95022217728511,
            "std": 14.921498240395426,
            "median": 67.0009894674034
          },
          "dist_pair13": {
            "mean": 119.6437451124938,
            "std": 46.3266675860022,
            "median": 120.1938659834843
          },
          "dist_pair14": {
            "mean": 144.44930608178814,
            "std": 38.40867188311939,
            "median": 141.57175349740368
          },
          "dist_pair15": {
            "mean": 157.56236017376884,
            "std": 57.538631499587595,
            "median": 156.70498126630068
          },
          "dist_pair16": {
            "mean": 71.0503935588527,
            "std": 43.551005830843266,
            "median": 68.99756259713746
          },
          "dist_pair17": {
            "mean": 68.93459352511968,
            "std": 23.89655442979931,
            "median": 64.56692792950055
          },
          "dist_pair18": {
            "mean": 38.684496970662735,
            "std": 51.54593715175581,
            "median": 10.820118663032769
          },
          "dist_pair19": {
            "mean": 211.52166474685654,
            "std": 58.13406798336976,
            "median": 224.53883498215717
          },
          "dist_pair20": {
            "mean": 91.73771239596782,
            "std": 25.840661306041053,
            "median": 93.12300935273943
          },
          "dist_pair21": {
            "mean": 110.80479911363742,
            "std": 28.770923930447466,
            "median": 123.85486184810841
          },
          "dist_pair22": {
            "mean": 242.09254522864128,
            "std": 36.388364531371735,
            "median": 239.24277486472278
          },
          "dist_pair23": {
            "mean": 99.56805749346525,
            "std": 17.427694722628203,
            "median": 103.08945016207804
          },
          "dist_pair24": {
            "mean": 134.78513241938361,
            "std": 9.980055002433554,
            "median": 135.50728923226262
          },
          "dist_pair25": {
            "mean": 201.6900865697877,
            "std": 38.170545137010514,
            "median": 191.78090510319916
          },
          "dist_pair26": {
            "mean": 123.52162269355452,
            "std": 29.408574735125843,
            "median": 109.26238728883607
          },
          "dist_pair27": {
            "mean": 87.17684152088835,
            "std": 11.271882758174764,
            "median": 84.92412890817069
          },
          "centroid_speed": {
            "mean": 172.81718526726917,
            "std": 118.98679476507945,
            "median": 146.84271749505615
          },
          "body_orientation": {
            "mean": -0.045101412984178434,
            "std": 0.31260666444722635,
            "median": 0.03654189589066691
          },
          "elongation": {
            "mean": 2.332834922553773,
            "std": 0.5725372668744589,
            "median": 2.269571248482415
          },
          "angular_velocity": {
            "mean": 0.3920485090635504,
            "std": 8.869466529679505,
            "median": 0.02284729848200967
          },
          "movement_entropy": {
            "mean": 0.04630876375910394,
            "std": 0.01102529091144415,
            "median": 0.05026793156857691
          },
          "speed_mean_window": {
            "mean": 310.94623567087507,
            "std": 115.3239917291519,
            "median": 275.82052243047536
          },
          "speed_std_window": {
            "mean": 451.32388275683246,
            "std": 115.79012181136174,
            "median": 439.45764655365986
          },
          "speed_max_window": {
            "mean": 2169.954766217196,
            "std": 558.8778451831347,
            "median": 1906.8322770862117
          },
          "speed_p90_window": {
            "mean": 979.8729292717181,
            "std": 290.008724726982,
            "median": 957.2721681001359
          },
          "dist_mean_window": {
            "mean": 117.69055538370063,
            "std": 11.10544567385177,
            "median": 119.63394053222954
          },
          "dist_std_window": {
            "mean": 64.24722246389454,
            "std": 5.126113633721293,
            "median": 63.9129625411682
          },
          "angular_vel_mean_window": {
            "mean": 4.5360877568496,
            "std": 4.878287840874373,
            "median": 3.075132724322319
          },
          "angular_vel_max_window": {
            "mean": 23.033550752491916,
            "std": 29.274408130375463,
            "median": 9.92696449176187
          }
        }
      },
      "state_1": {
        "occurrence_rate": 0.18493785939528845,
        "total_frames": 997,
        "total_duration_sec": 33.233333333333334,
        "n_bouts": 153,
        "mean_bout_duration_sec": 0.21721132897603485,
        "median_bout_duration_sec": 0.1,
        "max_bout_duration_sec": 2.066666666666667,
        "feature_profile": {
          "speed_kp0": {
            "mean": 347.75180969038314,
            "std": 548.8590344975937,
            "median": 115.7067209224512
          },
          "speed_kp1": {
            "mean": 191.29210267340662,
            "std": 264.3223178747979,
            "median": 87.90282427630716
          },
          "speed_kp2": {
            "mean": 420.3529318096679,
            "std": 616.1632361029052,
            "median": 145.6597657961085
          },
          "speed_kp3": {
            "mean": 110.49729738542355,
            "std": 149.76437160579206,
            "median": 64.0395924809765
          },
          "speed_kp4": {
            "mean": 439.32457200307476,
            "std": 555.7347122890712,
            "median": 240.72083918224365
          },
          "speed_kp5": {
            "mean": 778.8759224897392,
            "std": 851.1396526142619,
            "median": 468.5554444191665
          },
          "speed_kp6": {
            "mean": 525.1351130649242,
            "std": 710.3741699008523,
            "median": 200.49482037596303
          },
          "speed_kp7": {
            "mean": 153.28847996827164,
            "std": 384.49261629248605,
            "median": 14.537524518948553
          },
          "dist_pair0": {
            "mean": 26.87471010164386,
            "std": 23.729866805071364,
            "median": 17.77746121434397
          },
          "dist_pair1": {
            "mean": 40.47892427053795,
            "std": 31.04988111111987,
            "median": 30.286630297137638
          },
          "dist_pair2": {
            "mean": 38.06233265123944,
            "std": 17.00346855471036,
            "median": 35.10448538284279
          },
          "dist_pair3": {
            "mean": 63.897382864305975,
            "std": 37.24284005423974,
            "median": 55.68406591838105
          },
          "dist_pair4": {
            "mean": 99.53484536647905,
            "std": 67.2295839786941,
            "median": 75.31512303882766
          },
          "dist_pair5": {
            "mean": 129.11655759274154,
            "std": 68.4847348183135,
            "median": 113.56057041225132
          },
          "dist_pair6": {
            "mean": 151.93258500803756,
            "std": 35.68263445532678,
            "median": 153.06807571912532
          },
          "dist_pair7": {
            "mean": 43.558327004323466,
            "std": 31.31545473483136,
            "median": 34.99655896236728
          },
          "dist_pair8": {
            "mean": 35.50915894329523,
            "std": 14.723518906467328,
            "median": 34.06451020197644
          },
          "dist_pair9": {
            "mean": 59.621807568770656,
            "std": 37.415103646990616,
            "median": 50.55108564084762
          },
          "dist_pair10": {
            "mean": 100.33617309352469,
            "std": 69.04943438731097,
            "median": 77.34352232949104
          },
          "dist_pair11": {
            "mean": 135.08303852874178,
            "std": 70.7703341158421,
            "median": 129.70260756114158
          },
          "dist_pair12": {
            "mean": 156.93865848709885,
            "std": 30.55513296063141,
            "median": 156.7018570864244
          },
          "dist_pair13": {
            "mean": 52.65414878481345,
            "std": 24.009875480666754,
            "median": 47.5481246002845
          },
          "dist_pair14": {
            "mean": 79.4461254644754,
            "std": 36.04509887962966,
            "median": 74.49388885248078
          },
          "dist_pair15": {
            "mean": 109.18212648497843,
            "std": 69.24884990509352,
            "median": 96.1541165931839
          },
          "dist_pair16": {
            "mean": 139.94388359543655,
            "std": 71.75380284178753,
            "median": 125.95671338417955
          },
          "dist_pair17": {
            "mean": 162.44148136116613,
            "std": 42.26155902520077,
            "median": 153.86166988241783
          },
          "dist_pair18": {
            "mean": 52.69058467270619,
            "std": 39.79884069694835,
            "median": 38.01972180665625
          },
          "dist_pair19": {
            "mean": 91.72858845008048,
            "std": 70.64896364076743,
            "median": 62.50754587404326
          },
          "dist_pair20": {
            "mean": 120.40241197696129,
            "std": 70.232016687764,
            "median": 118.23342632724528
          },
          "dist_pair21": {
            "mean": 144.7073743691456,
            "std": 28.023675615712946,
            "median": 146.69515826525245
          },
          "dist_pair22": {
            "mean": 110.72093829498075,
            "std": 74.72558298618011,
            "median": 93.48411478843435
          },
          "dist_pair23": {
            "mean": 113.06196020554525,
            "std": 63.654250164521365,
            "median": 108.80121059329745
          },
          "dist_pair24": {
            "mean": 138.62250835216489,
            "std": 39.456120071124644,
            "median": 138.57152458885503
          },
          "dist_pair25": {
            "mean": 145.94482095809698,
            "std": 67.14891559532168,
            "median": 157.63768010054903
          },
          "dist_pair26": {
            "mean": 137.1693014930166,
            "std": 38.31676762744238,
            "median": 140.88509431576566
          },
          "dist_pair27": {
            "mean": 125.87314175658912,
            "std": 58.77832202427476,
            "median": 110.57642555456333
          },
          "centroid_speed": {
            "mean": 210.46969809103564,
            "std": 144.06888630034575,
            "median": 181.71905566972464
          },
          "body_orientation": {
            "mean": -0.9288504468674447,
            "std": 0.6818776373195102,
            "median": -0.8373862816245967
          },
          "elongation": {
            "mean": 2.684690073546455,
            "std": 1.424843638340476,
            "median": 2.310156924469142
          },
          "angular_velocity": {
            "mean": -0.28987919467659207,
            "std": 17.528384433401566,
            "median": -0.1313897151818244
          },
          "movement_entropy": {
            "mean": 0.03229280781649928,
            "std": 0.0076122972261091935,
            "median": 0.030188590350656158
          },
          "speed_mean_window": {
            "mean": 408.67655323987475,
            "std": 142.57238207542974,
            "median": 397.8758531785149
          },
          "speed_std_window": {
            "mean": 612.9221978678441,
            "std": 145.12281254945887,
            "median": 615.649079754066
          },
          "speed_max_window": {
            "mean": 3216.737326912525,
            "std": 620.5515960463397,
            "median": 3340.271663260776
          },
          "speed_p90_window": {
            "mean": 1212.114223537783,
            "std": 435.1899703848422,
            "median": 1131.3053720356886
          },
          "dist_mean_window": {
            "mean": 101.5476430927029,
            "std": 14.16847331697863,
            "median": 102.92950384038161
          },
          "dist_std_window": {
            "mean": 63.99877866552042,
            "std": 6.7524602351895595,
            "median": 64.25872657361504
          },
          "angular_vel_mean_window": {
            "mean": 7.706964296831562,
            "std": 7.781835551669057,
            "median": 4.126651972456038
          },
          "angular_vel_max_window": {
            "mean": 38.802359148797315,
            "std": 34.32300863835156,
            "median": 23.367812363003974
          }
        }
      },
      "state_2": {
        "occurrence_rate": 0.32276015581524764,
        "total_frames": 1740,
        "total_duration_sec": 58.0,
        "n_bouts": 68,
        "mean_bout_duration_sec": 0.8529411764705883,
        "median_bout_duration_sec": 0.1,
        "max_bout_duration_sec": 28.333333333333332,
        "feature_profile": {
          "speed_kp0": {
            "mean": 281.0625525369006,
            "std": 391.8384085271197,
            "median": 129.82192570801507
          },
          "speed_kp1": {
            "mean": 133.926288108103,
            "std": 207.2111632975212,
            "median": 61.05840863070216
          },
          "speed_kp2": {
            "mean": 349.8987969766233,
            "std": 397.93924613765995,
            "median": 197.92874046733255
          },
          "speed_kp3": {
            "mean": 63.22355480909188,
            "std": 84.81663348507234,
            "median": 34.47375547406236
          },
          "speed_kp4": {
            "mean": 190.84942194088222,
            "std": 295.53807947376254,
            "median": 54.51582714525705
          },
          "speed_kp5": {
            "mean": 387.7946569566251,
            "std": 539.6757740872152,
            "median": 176.47135540967585
          },
          "speed_kp6": {
            "mean": 741.0118035047841,
            "std": 754.4848435722535,
            "median": 501.2205194487511
          },
          "speed_kp7": {
            "mean": 116.95032782425014,
            "std": 308.41913450422686,
            "median": 13.984795208656973
          },
          "dist_pair0": {
            "mean": 26.81279189366744,
            "std": 26.200262093549668,
            "median": 19.713167669441024
          },
          "dist_pair1": {
            "mean": 35.982530160728544,
            "std": 28.896513834058176,
            "median": 28.05266941026943
          },
          "dist_pair2": {
            "mean": 31.384582966005272,
            "std": 22.538399565681296,
            "median": 28.190655761286607
          },
          "dist_pair3": {
            "mean": 42.07851955368555,
            "std": 23.77797790694146,
            "median": 37.00279407738175
          },
          "dist_pair4": {
            "mean": 48.70028538815087,
            "std": 32.20934551959209,
            "median": 43.24621747386523
          },
          "dist_pair5": {
            "mean": 88.05684729036183,
            "std": 51.41958948369495,
            "median": 73.10613085198581
          },
          "dist_pair6": {
            "mean": 93.52779289460877,
            "std": 26.713966035425102,
            "median": 94.0416106899182
          },
          "dist_pair7": {
            "mean": 34.29027340555964,
            "std": 24.62003222460154,
            "median": 26.80089048695317
          },
          "dist_pair8": {
            "mean": 26.804318396758138,
            "std": 14.983351845394866,
            "median": 24.350092138059317
          },
          "dist_pair9": {
            "mean": 35.07441199873064,
            "std": 17.26575315154812,
            "median": 32.01557331087452
          },
          "dist_pair10": {
            "mean": 44.11633593999294,
            "std": 30.531915497309175,
            "median": 37.49596953367367
          },
          "dist_pair11": {
            "mean": 90.829132975701,
            "std": 53.072448370377366,
            "median": 76.45511875925104
          },
          "dist_pair12": {
            "mean": 100.30296246865042,
            "std": 23.548894680367493,
            "median": 95.51820256466044
          },
          "dist_pair13": {
            "mean": 40.44685856102698,
            "std": 19.43385754123409,
            "median": 40.463040649578836
          },
          "dist_pair14": {
            "mean": 50.96566860371014,
            "std": 24.515090301681493,
            "median": 45.02451887561021
          },
          "dist_pair15": {
            "mean": 56.76652218956043,
            "std": 33.46756967346468,
            "median": 51.60103508226183
          },
          "dist_pair16": {
            "mean": 96.09308386231062,
            "std": 53.479402724044704,
            "median": 89.06377071383858
          },
          "dist_pair17": {
            "mean": 104.42753838200912,
            "std": 30.964734670897663,
            "median": 104.0636838213838
          },
          "dist_pair18": {
            "mean": 30.445460544290647,
            "std": 15.00941983755745,
            "median": 30.086003507996146
          },
          "dist_pair19": {
            "mean": 41.263055630178734,
            "std": 29.505640203150527,
            "median": 30.406731120094477
          },
          "dist_pair20": {
            "mean": 82.99254745044942,
            "std": 49.39885011257881,
            "median": 66.86396061532766
          },
          "dist_pair21": {
            "mean": 91.62269615745858,
            "std": 17.480064501921664,
            "median": 86.65394405040482
          },
          "dist_pair22": {
            "mean": 47.81460069872843,
            "std": 32.62281511231938,
            "median": 43.207234837461456
          },
          "dist_pair23": {
            "mean": 82.56332815756069,
            "std": 53.78668127419081,
            "median": 68.75460520969403
          },
          "dist_pair24": {
            "mean": 96.90654548554436,
            "std": 21.054601043077135,
            "median": 90.19114748926148
          },
          "dist_pair25": {
            "mean": 90.50777642623198,
            "std": 55.95528879667532,
            "median": 76.25959375574607
          },
          "dist_pair26": {
            "mean": 100.74331162359185,
            "std": 25.55370996176652,
            "median": 104.10214863941101
          },
          "dist_pair27": {
            "mean": 80.97385794713705,
            "std": 35.43403869572671,
            "median": 85.15028322979455
          },
          "centroid_speed": {
            "mean": 163.89764224850202,
            "std": 113.30487848469825,
            "median": 141.80246620052338
          },
          "body_orientation": {
            "mean": -0.5925563561684689,
            "std": 0.42214815604753125,
            "median": -0.6518649439419789
          },
          "elongation": {
            "mean": 2.6499406654071676,
            "std": 1.2306700634228296,
            "median": 2.3309961036675757
          },
          "angular_velocity": {
            "mean": 0.036294101637189914,
            "std": 11.158518639030607,
            "median": -0.009331690517134159
          },
          "movement_entropy": {
            "mean": 0.03923868878530486,
            "std": 0.008276267725280763,
            "median": 0.03726569047600996
          },
          "speed_mean_window": {
            "mean": 284.92388083986805,
            "std": 86.51949884157713,
            "median": 273.62866548930765
          },
          "speed_std_window": {
            "mean": 449.5129503684564,
            "std": 101.84930345895597,
            "median": 451.13070929598587
          },
          "speed_max_window": {
            "mean": 2538.421144285508,
            "std": 477.18986322272656,
            "median": 2562.48114584881
          },
          "speed_p90_window": {
            "mean": 828.1110053066145,
            "std": 257.38706931947297,
            "median": 808.6017962517401
          },
          "dist_mean_window": {
            "mean": 66.7887230290732,
            "std": 10.905497759911857,
            "median": 64.25080565956281
          },
          "dist_std_window": {
            "mean": 45.22611171631405,
            "std": 8.875472471310834,
            "median": 45.03011842383724
          },
          "angular_vel_mean_window": {
            "mean": 5.034224583546277,
            "std": 3.473497060190995,
            "median": 4.306064630957174
          },
          "angular_vel_max_window": {
            "mean": 26.221526979394973,
            "std": 23.160807891335665,
            "median": 19.55930487103701
          }
        }
      },
      "state_3": {
        "occurrence_rate": 0.1930996104618809,
        "total_frames": 1041,
        "total_duration_sec": 34.7,
        "n_bouts": 63,
        "mean_bout_duration_sec": 0.5507936507936508,
        "median_bout_duration_sec": 0.06666666666666667,
        "max_bout_duration_sec": 15.333333333333334,
        "feature_profile": {
          "speed_kp0": {
            "mean": 31.772932059314357,
            "std": 84.31851187576876,
            "median": 10.538536776990519
          },
          "speed_kp1": {
            "mean": 23.03111346068801,
            "std": 65.0940060814363,
            "median": 11.892121678601892
          },
          "speed_kp2": {
            "mean": 53.932194707472235,
            "std": 121.63396589092417,
            "median": 19.766707577222743
          },
          "speed_kp3": {
            "mean": 38.6268752363797,
            "std": 86.41386819828803,
            "median": 23.72653791571097
          },
          "speed_kp4": {
            "mean": 378.1508396393389,
            "std": 351.61583052925005,
            "median": 308.4110243222046
          },
          "speed_kp5": {
            "mean": 511.2858825797665,
            "std": 802.8602700851281,
            "median": 75.9295673633815
          },
          "speed_kp6": {
            "mean": 162.5958389220662,
            "std": 268.7285003996457,
            "median": 86.09860668816319
          },
          "speed_kp7": {
            "mean": 18.23363910751484,
            "std": 34.06724349385085,
            "median": 12.74872636434308
          },
          "dist_pair0": {
            "mean": 13.316579728920626,
            "std": 6.048476038535779,
            "median": 11.436403065146964
          },
          "dist_pair1": {
            "mean": 28.243045864580697,
            "std": 5.193329971513491,
            "median": 29.675876568860428
          },
          "dist_pair2": {
            "mean": 37.45743937401444,
            "std": 4.6819928339462376,
            "median": 37.753668774952594
          },
          "dist_pair3": {
            "mean": 73.76780595235876,
            "std": 28.460729283476972,
            "median": 77.5763472419658
          },
          "dist_pair4": {
            "mean": 224.80563577489997,
            "std": 36.821213454374195,
            "median": 241.7620147165467
          },
          "dist_pair5": {
            "mean": 211.36263452108307,
            "std": 15.518552264034202,
            "median": 213.80087846369435
          },
          "dist_pair6": {
            "mean": 131.42924221974937,
            "std": 6.12935846924736,
            "median": 132.07987516201985
          },
          "dist_pair7": {
            "mean": 35.6384340816384,
            "std": 6.164713438370424,
            "median": 36.16161843678488
          },
          "dist_pair8": {
            "mean": 48.306373052596406,
            "std": 6.8147676126399865,
            "median": 49.32944197176085
          },
          "dist_pair9": {
            "mean": 73.0871456522276,
            "std": 28.623700223442146,
            "median": 75.91225178430423
          },
          "dist_pair10": {
            "mean": 232.33833246384603,
            "std": 37.15431509875589,
            "median": 250.10926473444331
          },
          "dist_pair11": {
            "mean": 215.68653692415225,
            "std": 14.555280978987499,
            "median": 217.49050159080437
          },
          "dist_pair12": {
            "mean": 136.18548194942653,
            "std": 5.909315100382124,
            "median": 136.8895227526231
          },
          "dist_pair13": {
            "mean": 42.67116702988712,
            "std": 5.6051528611237025,
            "median": 43.42282381570615
          },
          "dist_pair14": {
            "mean": 99.17445573303407,
            "std": 30.09820603465607,
            "median": 104.97048912359651
          },
          "dist_pair15": {
            "mean": 236.26296223892993,
            "std": 36.808271861012464,
            "median": 252.3900793150492
          },
          "dist_pair16": {
            "mean": 230.42935604027497,
            "std": 19.06781231313599,
            "median": 234.33417979171028
          },
          "dist_pair17": {
            "mean": 150.40248923839803,
            "std": 8.94080347327806,
            "median": 152.04147594082607
          },
          "dist_pair18": {
            "mean": 82.29791337032553,
            "std": 26.145881628967768,
            "median": 87.64121103643424
          },
          "dist_pair19": {
            "mean": 196.14022826471245,
            "std": 36.16832723052254,
            "median": 208.34116616450228
          },
          "dist_pair20": {
            "mean": 193.24775644648238,
            "std": 14.164561756692489,
            "median": 194.95783647660133
          },
          "dist_pair21": {
            "mean": 113.13641064848605,
            "std": 11.260345481843496,
            "median": 111.91512047730292
          },
          "dist_pair22": {
            "mean": 196.65164910334212,
            "std": 37.436621643292426,
            "median": 207.61233845970207
          },
          "dist_pair23": {
            "mean": 156.63237986755271,
            "std": 26.385863548884107,
            "median": 155.80245617887726
          },
          "dist_pair24": {
            "mean": 88.84536888585522,
            "std": 18.086742772252258,
            "median": 84.44727661627142
          },
          "dist_pair25": {
            "mean": 96.98165223777475,
            "std": 29.27604296170125,
            "median": 102.60133332280188
          },
          "dist_pair26": {
            "mean": 113.88310985738268,
            "std": 27.700718570586357,
            "median": 128.29503794062182
          },
          "dist_pair27": {
            "mean": 82.93014760525402,
            "std": 9.490694193496582,
            "median": 82.33150149991226
          },
          "centroid_speed": {
            "mean": 103.0909796698535,
            "std": 98.63075962910575,
            "median": 70.35127733751216
          },
          "body_orientation": {
            "mean": -0.46548857672419425,
            "std": 0.2547749847260287,
            "median": -0.4574444603609778
          },
          "elongation": {
            "mean": 2.9784374689292563,
            "std": 0.7349855575003268,
            "median": 2.76563576961424
          },
          "angular_velocity": {
            "mean": 0.16674255173716324,
            "std": 4.53067945944448,
            "median": 0.03868692524422235
          },
          "movement_entropy": {
            "mean": 0.04859245896939606,
            "std": 0.022551967147921986,
            "median": 0.042284035242942615
          },
          "speed_mean_window": {
            "mean": 162.3468150104169,
            "std": 82.2466509955182,
            "median": 139.51640982312506
          },
          "speed_std_window": {
            "mean": 345.55391269275367,
            "std": 170.51699410400943,
            "median": 299.9846779790857
          },
          "speed_max_window": {
            "mean": 2252.2676086588676,
            "std": 1034.6613980325023,
            "median": 2076.885325192089
          },
          "speed_p90_window": {
            "mean": 492.2815122237534,
            "std": 279.4525491643978,
            "median": 436.8801007941387
          },
          "dist_mean_window": {
            "mean": 123.83100106475545,
            "std": 9.819826448196945,
            "median": 127.23255074278926
          },
          "dist_std_window": {
            "mean": 73.12406356469684,
            "std": 3.8717785027285645,
            "median": 74.02006836420517
          },
          "angular_vel_mean_window": {
            "mean": 1.6275690224562345,
            "std": 1.9955870544461782,
            "median": 1.2355193834764517
          },
          "angular_vel_max_window": {
            "mean": 8.273603270933776,
            "std": 16.438269342140437,
            "median": 5.641765085069825
          }
        }
      },
      "state_4": {
        "occurrence_rate": 0.2125765164162493,
        "total_frames": 1146,
        "total_duration_sec": 38.2,
        "n_bouts": 85,
        "mean_bout_duration_sec": 0.44941176470588234,
        "median_bout_duration_sec": 0.16666666666666666,
        "max_bout_duration_sec": 3.3666666666666667,
        "feature_profile": {
          "speed_kp0": {
            "mean": 1060.3401085998958,
            "std": 876.3888665442281,
            "median": 910.3206640439769
          },
          "speed_kp1": {
            "mean": 970.1767186539781,
            "std": 881.2544095850777,
            "median": 749.4064264967676
          },
          "speed_kp2": {
            "mean": 1099.6949888040801,
            "std": 988.2750854644247,
            "median": 906.3653961003918
          },
          "speed_kp3": {
            "mean": 186.41977324966098,
            "std": 333.25485605630973,
            "median": 87.24503559324651
          },
          "speed_kp4": {
            "mean": 330.38303202124644,
            "std": 545.3867468938198,
            "median": 81.33590975592551
          },
          "speed_kp5": {
            "mean": 715.6391907309952,
            "std": 707.1177385041849,
            "median": 542.3487514598987
          },
          "speed_kp6": {
            "mean": 741.6867395254939,
            "std": 836.0965567949045,
            "median": 319.66880330211484
          },
          "speed_kp7": {
            "mean": 36.598582395724335,
            "std": 80.26332344769423,
            "median": 18.085268852058817
          },
          "dist_pair0": {
            "mean": 124.03265771148878,
            "std": 69.35886263575645,
            "median": 122.55521667349599
          },
          "dist_pair1": {
            "mean": 132.84791489326287,
            "std": 82.77857145434784,
            "median": 129.48182385220397
          },
          "dist_pair2": {
            "mean": 160.6763384366426,
            "std": 61.617146237525176,
            "median": 180.89290318229757
          },
          "dist_pair3": {
            "mean": 151.08841811353443,
            "std": 56.48661041497055,
            "median": 167.75352797704903
          },
          "dist_pair4": {
            "mean": 144.78243907965734,
            "std": 57.64425906167944,
            "median": 140.93217360781804
          },
          "dist_pair5": {
            "mean": 125.59208797099603,
            "std": 59.65295735673841,
            "median": 124.49340048125562
          },
          "dist_pair6": {
            "mean": 74.80451625113007,
            "std": 35.921994840442856,
            "median": 73.03012907224968
          },
          "dist_pair7": {
            "mean": 116.52922950557371,
            "std": 72.16630639111563,
            "median": 100.82307023723459
          },
          "dist_pair8": {
            "mean": 80.70269246025195,
            "std": 63.48110043037022,
            "median": 55.39924494942923
          },
          "dist_pair9": {
            "mean": 85.11545895946881,
            "std": 59.36668692494082,
            "median": 67.12281929799585
          },
          "dist_pair10": {
            "mean": 122.81664623596333,
            "std": 66.10940513403546,
            "median": 120.05380551953469
          },
          "dist_pair11": {
            "mean": 121.29663692321583,
            "std": 57.86730317892122,
            "median": 119.07701580559186
          },
          "dist_pair12": {
            "mean": 108.64030961956784,
            "std": 51.67048822518406,
            "median": 106.70997231160594
          },
          "dist_pair13": {
            "mean": 110.02003121384081,
            "std": 66.06751993749828,
            "median": 86.6704967264343
          },
          "dist_pair14": {
            "mean": 117.49969004912906,
            "std": 60.48705333507073,
            "median": 102.99090556894839
          },
          "dist_pair15": {
            "mean": 178.17236593853434,
            "std": 63.98127484033317,
            "median": 183.95569749688178
          },
          "dist_pair16": {
            "mean": 132.25960311211497,
            "std": 62.54566030595381,
            "median": 128.83605453220818
          },
          "dist_pair17": {
            "mean": 117.53354858073273,
            "std": 57.8583907441977,
            "median": 106.99166108676958
          },
          "dist_pair18": {
            "mean": 42.38260247055419,
            "std": 38.599360191880635,
            "median": 28.866407516559022
          },
          "dist_pair19": {
            "mean": 133.4254792602134,
            "std": 72.35080959676759,
            "median": 146.25189579367674
          },
          "dist_pair20": {
            "mean": 106.67464546190124,
            "std": 66.75785549208881,
            "median": 94.54898716969149
          },
          "dist_pair21": {
            "mean": 140.99059672007652,
            "std": 19.807964684206258,
            "median": 141.08911616766795
          },
          "dist_pair22": {
            "mean": 129.4974086386882,
            "std": 73.80580211404612,
            "median": 142.94711395899031
          },
          "dist_pair23": {
            "mean": 94.04457172998255,
            "std": 60.66963114079953,
            "median": 88.4517121394075
          },
          "dist_pair24": {
            "mean": 126.7097742431822,
            "std": 23.562313816878685,
            "median": 120.08754389016953
          },
          "dist_pair25": {
            "mean": 143.9760031324028,
            "std": 62.32948548986232,
            "median": 158.04869114940456
          },
          "dist_pair26": {
            "mean": 123.1412129335906,
            "std": 32.36693248113186,
            "median": 116.4108596639311
          },
          "dist_pair27": {
            "mean": 99.68322934367642,
            "std": 35.50614246816188,
            "median": 90.51094689413188
          },
          "centroid_speed": {
            "mean": 347.3445846931946,
            "std": 220.49728271576734,
            "median": 303.29852891102314
          },
          "body_orientation": {
            "mean": -1.1461417586489597,
            "std": 1.0526628198945533,
            "median": -1.37205937974097
          },
          "elongation": {
            "mean": 2.5795769346129607,
            "std": 1.5636763072235833,
            "median": 2.0781481585666297
          },
          "angular_velocity": {
            "mean": -0.13465855533887236,
            "std": 33.363053919376576,
            "median": -0.021406349163981542
          },
          "movement_entropy": {
            "mean": 0.030820300082288598,
            "std": 0.0052624310641458455,
            "median": 0.030823071556948065
          },
          "speed_mean_window": {
            "mean": 597.4898006008932,
            "std": 120.43301827476492,
            "median": 595.7153867164276
          },
          "speed_std_window": {
            "mean": 763.1572986714539,
            "std": 105.28640747191362,
            "median": 765.1265419415197
          },
          "speed_max_window": {
            "mean": 3380.4913347006354,
            "std": 346.34981019293076,
            "median": 3428.7041828680485
          },
          "speed_p90_window": {
            "mean": 1747.1795250953253,
            "std": 329.66403503615845,
            "median": 1728.0342691816859
          },
          "dist_mean_window": {
            "mean": 117.11212994488781,
            "std": 12.403681200218017,
            "median": 119.2559932727084
          },
          "dist_std_window": {
            "mean": 63.5936084082638,
            "std": 5.677605048626245,
            "median": 62.74339784730526
          },
          "angular_vel_mean_window": {
            "mean": 16.067960987562415,
            "std": 11.177018362176167,
            "median": 17.14232439636381
          },
          "angular_vel_max_window": {
            "mean": 65.3445424532074,
            "std": 35.368801208001855,
            "median": 88.21535734502649
          }
        }
      }
    }
  },
  "transitions": {
    "transition_matrix": [
      [
        0.9207708779443254,
        0.01284796573875803,
        0.008565310492505354,
        0.0021413276231263384,
        0.055674518201284794
      ],
      [
        0.008032128514056224,
        0.8473895582329317,
        0.04417670682730924,
        0.04919678714859438,
        0.05120481927710843
      ],
      [
        0.0022988505747126436,
        0.02471264367816092,
        0.960919540229885,
        0.007471264367816092,
        0.004597701149425287
      ],
      [
        0.0019212295869356388,
        0.04514889529298751,
        0.013448607108549471,
        0.9394812680115274,
        0.0
      ],
      [
        0.019197207678883072,
        0.049738219895287955,
        0.005235602094240838,
        0.0,
        0.9258289703315882
      ]
    ],
    "transition_counts": [
      [
        430.0,
        6.0,
        4.0,
        1.0,
        26.0
      ],
      [
        8.0,
        844.0,
        44.0,
        49.0,
        51.0
      ],
      [
        4.0,
        43.0,
        1672.0,
        13.0,
        8.0
      ],
      [
        2.0,
        47.0,
        14.0,
        978.0,
        0.0
      ],
      [
        22.0,
        57.0,
        6.0,
        0.0,
        1061.0
      ]
    ],
    "state_labels": [
      0,
      1,
      2,
      3,
      4
    ],
    "top_transitions": [
      {
        "from_state": 4,
        "to_state": 1,
        "count": 57,
        "probability": 0.049738219895287955
      },
      {
        "from_state": 1,
        "to_state": 4,
        "count": 51,
        "probability": 0.05120481927710843
      },
      {
        "from_state": 1,
        "to_state": 3,
        "count": 49,
        "probability": 0.04919678714859438
      },
      {
        "from_state": 3,
        "to_state": 1,
        "count": 47,
        "probability": 0.04514889529298751
      },
      {
        "from_state": 1,
        "to_state": 2,
        "count": 44,
        "probability": 0.04417670682730924
      },
      {
        "from_state": 2,
        "to_state": 1,
        "count": 43,
        "probability": 0.02471264367816092
      },
      {
        "from_state": 0,
        "to_state": 4,
        "count": 26,
        "probability": 0.055674518201284794
      },
      {
        "from_state": 4,
        "to_state": 0,
        "count": 22,
        "probability": 0.019197207678883072
      },
      {
        "from_state": 3,
        "to_state": 2,
        "count": 14,
        "probability": 0.013448607108549471
      },
      {
        "from_state": 2,
        "to_state": 3,
        "count": 13,
        "probability": 0.007471264367816092
      }
    ]
  }
}