{
  "behavioral_states": {
    "n_states": 2,
    "states": {
      "state_0": {
        "occurrence_rate": 0.5234650343164533,
        "total_frames": 2822,
        "total_duration_sec": 94.06666666666666,
        "n_bouts": 216,
        "mean_bout_duration_sec": 0.43549382716049384,
        "median_bout_duration_sec": 0.1,
        "max_bout_duration_sec": 7.266666666666667,
        "feature_profile": {
          "speed_kp0": {
            "mean": 158.7485682415385,
            "std": 342.98920177826113,
            "median": 62.11463293365042
          },
          "speed_kp1": {
            "mean": 160.2983250582756,
            "std": 329.0556460252663,
            "median": 62.00896111286568
          },
          "speed_kp2": {
            "mean": 207.13181930753237,
            "std": 383.1062829740839,
            "median": 84.33694801951948
          },
          "speed_kp3": {
            "mean": 57.813628635419164,
            "std": 85.38044501055327,
            "median": 36.21983276200282
          },
          "speed_kp4": {
            "mean": 98.08211491418156,
            "std": 195.8628671195307,
            "median": 34.83500299352609
          },
          "speed_kp5": {
            "mean": 85.6115074820019,
            "std": 167.80874655591433,
            "median": 31.415728555510544
          },
          "speed_kp6": {
            "mean": 75.54097751437327,
            "std": 223.93733628301808,
            "median": 21.9493217126336
          },
          "speed_kp7": {
            "mean": 493.1173169624846,
            "std": 769.8421546986385,
            "median": 66.49838336388906
          },
          "dist_pair0": {
            "mean": 35.76795187248238,
            "std": 18.872113917109544,
            "median": 30.91603914134724
          },
          "dist_pair1": {
            "mean": 42.32939069273142,
            "std": 33.28290605422967,
            "median": 32.654982272628075
          },
          "dist_pair2": {
            "mean": 35.95362211893495,
            "std": 15.047475270796928,
            "median": 33.40932806268109
          },
          "dist_pair3": {
            "mean": 63.14932250945695,
            "std": 17.43153533919941,
            "median": 62.030916895376315
          },
          "dist_pair4": {
            "mean": 74.47341160957126,
            "std": 17.359798858873507,
            "median": 73.61454781861448
          },
          "dist_pair5": {
            "mean": 94.14092156708371,
            "std": 20.148656984099347,
            "median": 95.21998758870004
          },
          "dist_pair6": {
            "mean": 132.12394407447474,
            "std": 36.584674779675076,
            "median": 134.8144388720042
          },
          "dist_pair7": {
            "mean": 41.510013209373746,
            "std": 27.41187105980033,
            "median": 36.14338535339685
          },
          "dist_pair8": {
            "mean": 35.94650094719311,
            "std": 12.984913132442246,
            "median": 33.489418685202885
          },
          "dist_pair9": {
            "mean": 73.73359990470735,
            "std": 17.04965429600157,
            "median": 74.50689123879067
          },
          "dist_pair10": {
            "mean": 61.1775154865782,
            "std": 17.119262367608975,
            "median": 59.662499033413795
          },
          "dist_pair11": {
            "mean": 91.74315422437003,
            "std": 20.89790616934003,
            "median": 93.48202536989203
          },
          "dist_pair12": {
            "mean": 131.31483572127883,
            "std": 36.84604402079787,
            "median": 135.75027274401458
          },
          "dist_pair13": {
            "mean": 61.29314401513687,
            "std": 19.753338365196225,
            "median": 58.41123385716561
          },
          "dist_pair14": {
            "mean": 91.90225177730628,
            "std": 21.111686729038915,
            "median": 90.10343683266652
          },
          "dist_pair15": {
            "mean": 89.63825555534515,
            "std": 20.53416719452785,
            "median": 90.22484484742964
          },
          "dist_pair16": {
            "mean": 113.73744087551252,
            "std": 25.326195193967735,
            "median": 116.25454188139949
          },
          "dist_pair17": {
            "mean": 141.13085731994275,
            "std": 47.63806485741855,
            "median": 149.49311250637675
          },
          "dist_pair18": {
            "mean": 42.530518006395496,
            "std": 9.186912665296704,
            "median": 43.04726009934352
          },
          "dist_pair19": {
            "mean": 43.733990724316556,
            "std": 9.617623018979593,
            "median": 43.37221165896429
          },
          "dist_pair20": {
            "mean": 65.71348033321098,
            "std": 11.962122853362391,
            "median": 66.49705674810119
          },
          "dist_pair21": {
            "mean": 118.9784445535323,
            "std": 29.561503208757504,
            "median": 119.26321075001057
          },
          "dist_pair22": {
            "mean": 57.41515846422283,
            "std": 11.626274597875703,
            "median": 58.46887421996444
          },
          "dist_pair23": {
            "mean": 47.59680224221939,
            "std": 13.863393773590156,
            "median": 46.813855193353355
          },
          "dist_pair24": {
            "mean": 110.22142880399647,
            "std": 36.20256816552713,
            "median": 110.88779000845992
          },
          "dist_pair25": {
            "mean": 47.10423119319952,
            "std": 12.37890514230246,
            "median": 47.43015974224801
          },
          "dist_pair26": {
            "mean": 109.44706386670595,
            "std": 38.33795184745424,
            "median": 109.36381840393429
          },
          "dist_pair27": {
            "mean": 93.82559323059014,
            "std": 43.18195613283463,
            "median": 83.0580276291181
          },
          "centroid_speed": {
            "mean": 111.45212539126697,
            "std": 116.6771420552662,
            "median": 69.62749605813107
          },
          "body_orientation": {
            "mean": -0.45924491873606577,
            "std": 0.8346475311222967,
            "median": -0.32717756833147643
          },
          "elongation": {
            "mean": 2.291360183115912,
            "std": 0.7689828230451604,
            "median": 2.2587100558155226
          },
          "angular_velocity": {
            "mean": -0.20591382600197475,
            "std": 18.32949427960454,
            "median": 0.0020755772062072686
          },
          "movement_entropy": {
            "mean": 0.0768289140176676,
            "std": 0.13333982106052514,
            "median": 0.040827484281306274
          },
          "speed_mean_window": {
            "mean": 163.28523218195906,
            "std": 88.06656369653297,
            "median": 155.8672453081856
          },
          "speed_std_window": {
            "mean": 328.51590481537863,
            "std": 168.42957632429298,
            "median": 329.1949900433332
          },
          "speed_max_window": {
            "mean": 2156.3660142495214,
            "std": 1012.994314314404,
            "median": 2084.3119391280725
          },
          "speed_p90_window": {
            "mean": 386.1574992512491,
            "std": 298.55386752900836,
            "median": 278.4486026004048
          },
          "dist_mean_window": {
            "mean": 80.02802113420111,
            "std": 7.451744444462191,
            "median": 79.56522477906766
          },
          "dist_std_window": {
            "mean": 43.774492155844875,
            "std": 7.966247201815014,
            "median": 42.52395471531918
          },
          "angular_vel_mean_window": {
            "mean": 6.22595528479216,
            "std": 6.573125309146768,
            "median": 3.9128683429571662
          },
          "angular_vel_max_window": {
            "mean": 37.326320389698395,
            "std": 35.0184043351314,
            "median": 19.013831743727753
          }
        }
      },
      "state_1": {
        "occurrence_rate": 0.47653496568354664,
        "total_frames": 2569,
        "total_duration_sec": 85.63333333333334,
        "n_bouts": 216,
        "mean_bout_duration_sec": 0.39645061728395065,
        "median_bout_duration_sec": 0.1,
        "max_bout_duration_sec": 8.0,
        "feature_profile": {
          "speed_kp0": {
            "mean": 138.53707668544163,
            "std": 288.8900410183352,
            "median": 58.705846634518316
          },
          "speed_kp1": {
            "mean": 153.9370305262815,
            "std": 316.7171783018608,
            "median": 61.590725755138095
          },
          "speed_kp2": {
            "mean": 160.89802494048976,
            "std": 322.86156589550325,
            "median": 69.2318364682755
          },
          "speed_kp3": {
            "mean": 67.04034154558907,
            "std": 115.5957993735253,
            "median": 36.81081600080786
          },
          "speed_kp4": {
            "mean": 96.04894579876104,
            "std": 191.16632818014574,
            "median": 36.73477638337422
          },
          "speed_kp5": {
            "mean": 82.12816762428795,
            "std": 159.59268514646763,
            "median": 31.16292052610827
          },
          "speed_kp6": {
            "mean": 88.4002500630894,
            "std": 275.2590926444263,
            "median": 24.266525345002588
          },
          "speed_kp7": {
            "mean": 176.9330982099991,
            "std": 393.4905324263151,
            "median": 25.986891428929756
          },
          "dist_pair0": {
            "mean": 45.92424360117281,
            "std": 39.57510070680312,
            "median": 30.127316289609706
          },
          "dist_pair1": {
            "mean": 54.57784002640823,
            "std": 46.92582030311721,
            "median": 35.16584534215807
          },
          "dist_pair2": {
            "mean": 39.282538391478234,
            "std": 20.618271290545835,
            "median": 35.50706635766526
          },
          "dist_pair3": {
            "mean": 74.10557511296959,
            "std": 21.830596387014975,
            "median": 69.76557465928914
          },
          "dist_pair4": {
            "mean": 80.39680600427445,
            "std": 19.81409879771469,
            "median": 77.97853699617093
          },
          "dist_pair5": {
            "mean": 108.50127776426517,
            "std": 28.79214750100246,
            "median": 105.86716132750459
          },
          "dist_pair6": {
            "mean": 194.00329798095643,
            "std": 32.485526772842256,
            "median": 198.2739569165134
          },
          "dist_pair7": {
            "mean": 39.07960972943178,
            "std": 29.884768906368333,
            "median": 32.01504075980104
          },
          "dist_pair8": {
            "mean": 49.72892062448064,
            "std": 32.14498433310368,
            "median": 37.23849004196409
          },
          "dist_pair9": {
            "mean": 92.4417254657827,
            "std": 28.143382972301406,
            "median": 85.19054235043137
          },
          "dist_pair10": {
            "mean": 74.66920258838012,
            "std": 22.30613691896844,
            "median": 71.5087117029974
          },
          "dist_pair11": {
            "mean": 111.58321194722592,
            "std": 30.391637392847258,
            "median": 107.44018152386164
          },
          "dist_pair12": {
            "mean": 187.25755394217435,
            "std": 35.879683049659334,
            "median": 188.59115786974863
          },
          "dist_pair13": {
            "mean": 75.1418768758001,
            "std": 28.743464301666464,
            "median": 66.08116006688779
          },
          "dist_pair14": {
            "mean": 113.85913495563285,
            "std": 29.05231718534189,
            "median": 110.46818563680807
          },
          "dist_pair15": {
            "mean": 101.75036648298837,
            "std": 21.22461941172676,
            "median": 101.17884523613714
          },
          "dist_pair16": {
            "mean": 136.15413569959134,
            "std": 31.096591616860692,
            "median": 135.09891722454313
          },
          "dist_pair17": {
            "mean": 203.3694533269932,
            "std": 42.77542696777407,
            "median": 209.72168741197535
          },
          "dist_pair18": {
            "mean": 48.62161584544415,
            "std": 13.33783078102107,
            "median": 46.59850444967409
          },
          "dist_pair19": {
            "mean": 48.077064714273746,
            "std": 11.595962125639682,
            "median": 46.15804780713647
          },
          "dist_pair20": {
            "mean": 77.58857439454222,
            "std": 25.014497244584195,
            "median": 73.83195256187147
          },
          "dist_pair21": {
            "mean": 173.70584553579656,
            "std": 28.173642182317234,
            "median": 178.0004091311274
          },
          "dist_pair22": {
            "mean": 56.82622433168476,
            "std": 15.074253624653183,
            "median": 57.41219487705735
          },
          "dist_pair23": {
            "mean": 52.96168861484296,
            "std": 25.127966183197067,
            "median": 49.17966000757448
          },
          "dist_pair24": {
            "mean": 155.91089005862003,
            "std": 31.961239355401293,
            "median": 154.74231054404206
          },
          "dist_pair25": {
            "mean": 50.68422289320703,
            "std": 23.502505179336683,
            "median": 46.97788375538436
          },
          "dist_pair26": {
            "mean": 141.42246592800737,
            "std": 38.81711307767459,
            "median": 140.43208057544754
          },
          "dist_pair27": {
            "mean": 115.43080810569819,
            "std": 38.42173108586962,
            "median": 116.47887933596625
          },
          "centroid_speed": {
            "mean": 81.6025448716491,
            "std": 92.47304717301078,
            "median": 50.721205299078136
          },
          "body_orientation": {
            "mean": -0.6934669160307078,
            "std": 0.8461244126320501,
            "median": -0.5047416008904606
          },
          "elongation": {
            "mean": 2.698599826321706,
            "std": 1.0553438951213945,
            "median": 2.459187424810314
          },
          "angular_velocity": {
            "mean": 0.2508532892556284,
            "std": 9.47797687415495,
            "median": 0.0590373772550179
          },
          "movement_entropy": {
            "mean": 0.12585199767973157,
            "std": 0.1934547108044629,
            "median": 0.0518402048518143
          },
          "speed_mean_window": {
            "mean": 126.53540026331207,
            "std": 81.8881756425694,
            "median": 117.52297671442355
          },
          "speed_std_window": {
            "mean": 236.16505380417755,
            "std": 163.12302659416903,
            "median": 235.33256782406937
          },
          "speed_max_window": {
            "mean": 1598.8280477592773,
            "std": 1043.9838686425155,
            "median": 1622.7761625268574
          },
          "speed_p90_window": {
            "mean": 297.8345359711603,
            "std": 261.58536183456016,
            "median": 205.62731053948312
          },
          "dist_mean_window": {
            "mean": 92.879472917889,
            "std": 8.686212366510393,
            "median": 92.13675113394294
          },
          "dist_std_window": {
            "mean": 53.949413925372916,
            "std": 8.182572326135913,
            "median": 54.08411866955031
          },
          "angular_vel_mean_window": {
            "mean": 3.2436590213336673,
            "std": 4.477457311544682,
            "median": 1.2880007176063424
          },
          "angular_vel_max_window": {
            "mean": 23.138346761957052,
            "std": 31.643040932729658,
            "median": 6.583387057558938
          }
        }
      }
    }
  },
  "transitions": {
    "transition_matrix": [
      [
        0.923458540042523,
        0.07654145995747696
      ],
      [
        0.0837227414330218,
        0.9162772585669782
      ]
    ],
    "transition_counts": [
      [
        2606.0,
        216.0
      ],
      [
        215.0,
        2353.0
      ]
    ],
    "state_labels": [
      0,
      1
    ],
    "top_transitions": [
      {
        "from_state": 0,
        "to_state": 1,
        "count": 216,
        "probability": 0.07654145995747696
      },
      {
        "from_state": 1,
        "to_state": 0,
        "count": 215,
        "probability": 0.0837227414330218
      }
    ]
  }
}