{
  "behavioral_states": {
    "n_states": 2,
    "states": {
      "state_0": {
        "occurrence_rate": 0.7592283435355222,
        "total_frames": 4093,
        "total_duration_sec": 136.43333333333334,
        "n_bouts": 38,
        "mean_bout_duration_sec": 3.5903508771929826,
        "median_bout_duration_sec": 0.2833333333333333,
        "max_bout_duration_sec": 80.36666666666666,
        "feature_profile": {
          "speed_kp0": {
            "mean": 24.23784177017108,
            "std": 36.32925081403511,
            "median": 7.50048337442841
          },
          "speed_kp1": {
            "mean": 24.588157811246923,
            "std": 38.34181458005475,
            "median": 7.174424202479526
          },
          "speed_kp2": {
            "mean": 45.97930130504234,
            "std": 72.95387065973867,
            "median": 12.763977315542578
          },
          "speed_kp3": {
            "mean": 14.762602895856068,
            "std": 19.919294662280063,
            "median": 6.2992876420843515
          },
          "speed_kp4": {
            "mean": 17.219783174040213,
            "std": 35.0602249995977,
            "median": 7.624385505389778
          },
          "speed_kp5": {
            "mean": 16.40608030587747,
            "std": 29.712339261226454,
            "median": 7.84072948630771
          },
          "speed_kp6": {
            "mean": 8.809927928954309,
            "std": 32.71555429275255,
            "median": 2.2311457132285963
          },
          "speed_kp7": {
            "mean": 32.07922052273473,
            "std": 199.08656816492459,
            "median": 1.820419028855561
          },
          "dist_pair0": {
            "mean": 29.443641241461364,
            "std": 3.304660873064909,
            "median": 29.109686615276665
          },
          "dist_pair1": {
            "mean": 28.356374478791725,
            "std": 8.71303376309767,
            "median": 24.35006253587536
          },
          "dist_pair2": {
            "mean": 26.899166951393386,
            "std": 3.004433350036908,
            "median": 27.26409919296626
          },
          "dist_pair3": {
            "mean": 54.12490115721683,
            "std": 8.104548604525666,
            "median": 53.89209816553405
          },
          "dist_pair4": {
            "mean": 64.6414147042915,
            "std": 4.772964003295549,
            "median": 65.69521939045845
          },
          "dist_pair5": {
            "mean": 83.96732538751856,
            "std": 9.493598398237086,
            "median": 86.31046430427457
          },
          "dist_pair6": {
            "mean": 162.4391502793072,
            "std": 18.938270363884097,
            "median": 163.57601639416043
          },
          "dist_pair7": {
            "mean": 26.18568058660357,
            "std": 12.487114993196444,
            "median": 24.009923126617355
          },
          "dist_pair8": {
            "mean": 29.955864559744267,
            "std": 3.0111245218675027,
            "median": 29.984924991880607
          },
          "dist_pair9": {
            "mean": 71.14633862875014,
            "std": 5.154132344084934,
            "median": 71.46941841610061
          },
          "dist_pair10": {
            "mean": 54.48924842417017,
            "std": 7.98601087505463,
            "median": 55.19412861240125
          },
          "dist_pair11": {
            "mean": 87.10510958603113,
            "std": 7.833667598118577,
            "median": 89.02975944413043
          },
          "dist_pair12": {
            "mean": 167.81066703548066,
            "std": 19.735916043237665,
            "median": 166.04067575202183
          },
          "dist_pair13": {
            "mean": 46.20734994606721,
            "std": 9.375533708350973,
            "median": 42.985730392155745
          },
          "dist_pair14": {
            "mean": 79.41850559563481,
            "std": 8.86995609286739,
            "median": 80.17550102652388
          },
          "dist_pair15": {
            "mean": 77.00750256693676,
            "std": 12.669278175779546,
            "median": 74.07916910324673
          },
          "dist_pair16": {
            "mean": 103.68597316452865,
            "std": 8.884240183211155,
            "median": 102.7718759032505
          },
          "dist_pair17": {
            "mean": 180.35388495795797,
            "std": 22.67118415731921,
            "median": 178.57417827370602
          },
          "dist_pair18": {
            "mean": 42.61716478976305,
            "std": 3.211944403280613,
            "median": 43.07572874703145
          },
          "dist_pair19": {
            "mean": 39.3604695566319,
            "std": 2.9367766347969924,
            "median": 39.49943275068762
          },
          "dist_pair20": {
            "mean": 61.428513652467636,
            "std": 5.11435028208584,
            "median": 62.66204190927934
          },
          "dist_pair21": {
            "mean": 144.2522844074395,
            "std": 17.028666631638984,
            "median": 138.66717432786675
          },
          "dist_pair22": {
            "mean": 59.249396051190416,
            "std": 3.946957071243662,
            "median": 59.7892884355313
          },
          "dist_pair23": {
            "mean": 45.85471352467526,
            "std": 7.855624537775864,
            "median": 47.2298694789826
          },
          "dist_pair24": {
            "mean": 118.64616647819702,
            "std": 17.29489744551086,
            "median": 113.7901447371338
          },
          "dist_pair25": {
            "mean": 43.872475981021374,
            "std": 5.968489156631248,
            "median": 43.82754334637672
          },
          "dist_pair26": {
            "mean": 125.81406704600097,
            "std": 25.792923378448947,
            "median": 116.40023305847205
          },
          "dist_pair27": {
            "mean": 88.67746907895702,
            "std": 21.996156660554853,
            "median": 76.41960619207869
          },
          "centroid_speed": {
            "mean": 14.506788450606107,
            "std": 29.058983344609192,
            "median": 4.3533403517592335
          },
          "body_orientation": {
            "mean": -0.3419006938242146,
            "std": 0.7038491893931188,
            "median": -0.3174118269266899
          },
          "elongation": {
            "mean": 2.9197656873250746,
            "std": 0.5523633274992076,
            "median": 3.052459266085416
          },
          "angular_velocity": {
            "mean": -0.08110183200205984,
            "std": 5.235921365245012,
            "median": -0.00084234429605895
          },
          "movement_entropy": {
            "mean": 0.7631720265765285,
            "std": 0.7310821499538028,
            "median": 0.4788937006372709
          },
          "speed_mean_window": {
            "mean": 23.073932225203578,
            "std": 26.45116834313931,
            "median": 12.444286029913046
          },
          "speed_std_window": {
            "mean": 38.768271202097246,
            "std": 65.89729634706713,
            "median": 18.1912720895156
          },
          "speed_max_window": {
            "mean": 293.7656497425695,
            "std": 558.9205480779497,
            "median": 114.15125610434687
          },
          "speed_p90_window": {
            "mean": 48.46107795144166,
            "std": 52.373269250535245,
            "median": 28.32367489035573
          },
          "dist_mean_window": {
            "mean": 77.1644854000068,
            "std": 4.717112257683258,
            "median": 75.66836110258006
          },
          "dist_std_window": {
            "mean": 45.84356651558256,
            "std": 5.510752269562358,
            "median": 43.87413110363765
          },
          "angular_vel_mean_window": {
            "mean": 0.571974367772878,
            "std": 1.6530965475435504,
            "median": 0.07634071098725342
          },
          "angular_vel_max_window": {
            "mean": 6.52755708277608,
            "std": 21.30313093217957,
            "median": 0.314973694182098
          }
        }
      },
      "state_1": {
        "occurrence_rate": 0.24077165646447785,
        "total_frames": 1298,
        "total_duration_sec": 43.266666666666666,
        "n_bouts": 38,
        "mean_bout_duration_sec": 1.1385964912280702,
        "median_bout_duration_sec": 0.4666666666666667,
        "max_bout_duration_sec": 10.4,
        "feature_profile": {
          "speed_kp0": {
            "mean": 72.7169461265116,
            "std": 55.742668495243265,
            "median": 63.011257934358476
          },
          "speed_kp1": {
            "mean": 78.0833552344092,
            "std": 60.87511521297246,
            "median": 68.68085640706528
          },
          "speed_kp2": {
            "mean": 110.09780421088007,
            "std": 102.5799483058615,
            "median": 84.83796109525369
          },
          "speed_kp3": {
            "mean": 60.27776445624802,
            "std": 58.202002720189626,
            "median": 48.19500556198878
          },
          "speed_kp4": {
            "mean": 68.00368313601504,
            "std": 122.20328533377311,
            "median": 31.87450125532409
          },
          "speed_kp5": {
            "mean": 70.90749091174573,
            "std": 134.62073878424462,
            "median": 30.054464560679037
          },
          "speed_kp6": {
            "mean": 54.01401977777772,
            "std": 81.73490109822288,
            "median": 31.327412462871592
          },
          "speed_kp7": {
            "mean": 244.8749031870928,
            "std": 514.6147749722344,
            "median": 41.459156330092256
          },
          "dist_pair0": {
            "mean": 30.42369750884419,
            "std": 3.8524024394049685,
            "median": 29.837117655741565
          },
          "dist_pair1": {
            "mean": 35.237802926705136,
            "std": 10.494758129653315,
            "median": 32.74914545413789
          },
          "dist_pair2": {
            "mean": 36.89401734710405,
            "std": 12.14831192458198,
            "median": 32.7823014816972
          },
          "dist_pair3": {
            "mean": 73.72840610215064,
            "std": 16.679746473208052,
            "median": 71.12018175834942
          },
          "dist_pair4": {
            "mean": 83.23167784851599,
            "std": 14.487707939410518,
            "median": 79.64673200349314
          },
          "dist_pair5": {
            "mean": 107.31847278239658,
            "std": 17.46323913258105,
            "median": 103.56952781545247
          },
          "dist_pair6": {
            "mean": 181.6883346886668,
            "std": 42.4575255282444,
            "median": 185.71490939924786
          },
          "dist_pair7": {
            "mean": 37.92081075040247,
            "std": 11.032954587643742,
            "median": 35.54796357314155
          },
          "dist_pair8": {
            "mean": 38.430747610805916,
            "std": 11.001944618391517,
            "median": 35.62053263141138
          },
          "dist_pair9": {
            "mean": 85.44805357446016,
            "std": 12.506115623916708,
            "median": 83.72524139073198
          },
          "dist_pair10": {
            "mean": 75.50660750259135,
            "std": 17.45104099918693,
            "median": 73.38643666667735
          },
          "dist_pair11": {
            "mean": 110.21386212229949,
            "std": 16.451935546899268,
            "median": 108.36989729283243
          },
          "dist_pair12": {
            "mean": 184.36574388301008,
            "std": 40.54189477142092,
            "median": 189.8438308370735
          },
          "dist_pair13": {
            "mean": 66.55570317378717,
            "std": 12.8348306825233,
            "median": 65.5037861128501
          },
          "dist_pair14": {
            "mean": 107.40170230378831,
            "std": 15.34435343261116,
            "median": 109.14609379241341
          },
          "dist_pair15": {
            "mean": 109.55019694947808,
            "std": 16.204317410804098,
            "median": 108.81374577406362
          },
          "dist_pair16": {
            "mean": 138.74488112650303,
            "std": 15.380461574741457,
            "median": 138.9252334899209
          },
          "dist_pair17": {
            "mean": 207.3582023677507,
            "std": 46.10754676883093,
            "median": 220.1789270129218
          },
          "dist_pair18": {
            "mean": 49.21776769311012,
            "std": 7.441435225975585,
            "median": 48.18379186638141
          },
          "dist_pair19": {
            "mean": 48.35812721886363,
            "std": 7.436695595376975,
            "median": 47.170220782980834
          },
          "dist_pair20": {
            "mean": 75.26275946491448,
            "std": 9.351237753223755,
            "median": 74.1232842400772
          },
          "dist_pair21": {
            "mean": 157.76846174255627,
            "std": 33.804937302219095,
            "median": 162.41572317583314
          },
          "dist_pair22": {
            "mean": 52.30898581297785,
            "std": 11.96537674787246,
            "median": 55.1932163958009
          },
          "dist_pair23": {
            "mean": 44.10919931191055,
            "std": 8.750984677531225,
            "median": 45.358044305462286
          },
          "dist_pair24": {
            "mean": 129.48606511369195,
            "std": 35.36685208719848,
            "median": 139.01645607814277
          },
          "dist_pair25": {
            "mean": 46.697137166827964,
            "std": 8.126042242857032,
            "median": 46.60095869896777
          },
          "dist_pair26": {
            "mean": 131.25849036953855,
            "std": 32.12705426156422,
            "median": 133.7468001404497
          },
          "dist_pair27": {
            "mean": 103.10286793074788,
            "std": 32.591748910542584,
            "median": 108.13100414179412
          },
          "centroid_speed": {
            "mean": 64.18529351267716,
            "std": 68.13043236955463,
            "median": 44.51341918806033
          },
          "body_orientation": {
            "mean": -0.9078863399864119,
            "std": 0.8063632555596363,
            "median": -1.09220083513546
          },
          "elongation": {
            "mean": 2.9940732425744874,
            "std": 1.1501446665204274,
            "median": 2.985981791830482
          },
          "angular_velocity": {
            "mean": 0.23744869451903536,
            "std": 12.56249771898263,
            "median": -0.013271698089512007
          },
          "movement_entropy": {
            "mean": 0.13122843308953952,
            "std": 0.16674895909456408,
            "median": 0.0900003046672814
          },
          "speed_mean_window": {
            "mean": 94.72678780356848,
            "std": 47.00932486006154,
            "median": 92.39323707706751
          },
          "speed_std_window": {
            "mean": 163.42816724712205,
            "std": 123.58464343537898,
            "median": 111.27876972190288
          },
          "speed_max_window": {
            "mean": 1240.5492512992346,
            "std": 971.0785957410727,
            "median": 806.0115293803597
          },
          "speed_p90_window": {
            "mean": 178.65099672191016,
            "std": 91.49018915473425,
            "median": 162.2890850244749
          },
          "dist_mean_window": {
            "mean": 89.24410244074848,
            "std": 9.613465926065604,
            "median": 88.0959915757815
          },
          "dist_std_window": {
            "mean": 51.66462675922996,
            "std": 8.968143405258216,
            "median": 52.54949037199205
          },
          "angular_vel_mean_window": {
            "mean": 3.287905799444595,
            "std": 4.20484392933508,
            "median": 0.9611641616591411
          },
          "angular_vel_max_window": {
            "mean": 28.813641307963614,
            "std": 37.70025484916317,
            "median": 3.628397094346643
          }
        }
      }
    }
  },
  "transitions": {
    "transition_matrix": [
      [
        0.9909579667644184,
        0.009042033235581623
      ],
      [
        0.029275808936825885,
        0.9707241910631741
      ]
    ],
    "transition_counts": [
      [
        4055.0,
        37.0
      ],
      [
        38.0,
        1260.0
      ]
    ],
    "state_labels": [
      0,
      1
    ],
    "top_transitions": [
      {
        "from_state": 1,
        "to_state": 0,
        "count": 38,
        "probability": 0.029275808936825885
      },
      {
        "from_state": 0,
        "to_state": 1,
        "count": 37,
        "probability": 0.009042033235581623
      }
    ]
  }
}